[
    {
        "id": "186273",
        "time": "1766716608486",
        "appid": "1b51b8f467482286c40861dd86416bee",
        "session": "BVS2q",
        "bereich": "start",
        "item": "",
        "action": "enter",
        "value": "",
        "words": "0",
        "elementids": []
    },
    {
        "id": "186274",
        "time": "1766716642775",
        "appid": "1b51b8f467482286c40861dd86416bee",
        "session": "Sv2uf",
        "bereich": "start",
        "item": "",
        "action": "enter",
        "value": "",
        "words": "0",
        "elementids": []
    },
    {
        "id": "186275",
        "time": "1766716647674",
        "appid": "1b51b8f467482286c40861dd86416bee",
        "session": "Sv2uf",
        "bereich": "datenschutz-bestaetigen",
        "item": "",
        "action": "enter",
        "value": "",
        "words": "0",
        "elementids": []
    },
    {
        "id": "186276",
        "time": "1766716650594",
        "appid": "1b51b8f467482286c40861dd86416bee",
        "session": "Sv2uf",
        "bereich": "start",
        "item": "",
        "action": "enter",
        "value": "",
        "words": "0",
        "elementids": []
    },
    {
        "id": "186277",
        "time": "1766752744857",
        "appid": "dbc86f2e0999bb3fa381fdb82eb190b5",
        "session": "FArqN",
        "bereich": "start",
        "item": "",
        "action": "enter",
        "value": "",
        "words": "0",
        "elementids": []
    },
    {
        "id": "186278",
        "time": "1766752842901",
        "appid": "dbc86f2e0999bb3fa381fdb82eb190b5",
        "session": "FArqN",
        "bereich": "datenschutz-bestaetigen",
        "item": "",
        "action": "enter",
        "value": "",
        "words": "0",
        "elementids": []
    },
    {
        "id": "186279",
        "time": "1766752883536",
        "appid": "dbc86f2e0999bb3fa381fdb82eb190b5",
        "session": "FArqN",
        "bereich": "fragebogen",
        "item": "",
        "action": "enter",
        "value": "",
        "words": "0",
        "elementids": []
    },
    {
        "id": "186280",
        "time": "1766752927479",
        "appid": "dbc86f2e0999bb3fa381fdb82eb190b5",
        "session": "FArqN",
        "bereich": "home",
        "item": "",
        "action": "enter",
        "value": "",
        "words": "0",
        "elementids": []
    },
    {
        "id": "186281",
        "time": "1766752969253",
        "appid": "dbc86f2e0999bb3fa381fdb82eb190b5",
        "session": "FArqN",
        "bereich": "zu-den-texten",
        "item": "",
        "action": "enter",
        "value": "",
        "words": "0",
        "elementids": []
    },
    {
        "id": "186282",
        "time": "1766753018345",
        "appid": "dbc86f2e0999bb3fa381fdb82eb190b5",
        "session": "FArqN",
        "bereich": "titelblatt_dieleidendesjungenwerthers",
        "item": "",
        "action": "enter",
        "value": "dieleidendesjungenwerthers",
        "words": "0",
        "elementids": []
    },
    {
        "id": "186283",
        "time": "1766753064859",
        "appid": "dbc86f2e0999bb3fa381fdb82eb190b5",
        "session": "FArqN",
        "bereich": "reader_dieleidendesjungenwerthers",
        "item": "",
        "action": "enter",
        "value": "dieleidendesjungenwerthers",
        "words": "0",
        "elementids": []
    },
    {
        "id": "186284",
        "time": "1766753504736",
        "appid": "46ae996145b08dc892f3a467d20d920b",
        "session": "2vVCE",
        "bereich": "start",
        "item": "",
        "action": "enter",
        "value": "",
        "words": "0",
        "elementids": []
    },
    {
        "id": "186285",
        "time": "1766753726647",
        "appid": "46ae996145b08dc892f3a467d20d920b",
        "session": "2vVCE",
        "bereich": "datenschutz-bestaetigen",
        "item": "",
        "action": "enter",
        "value": "",
        "words": "0",
        "elementids": []
    },
    {
        "id": "186286",
        "time": "1766753789785",
        "appid": "46ae996145b08dc892f3a467d20d920b",
        "session": "2vVCE",
        "bereich": "fragebogen",
        "item": "",
        "action": "enter",
        "value": "",
        "words": "0",
        "elementids": []
    },
    {
        "id": "186287",
        "time": "1766753920002",
        "appid": "46ae996145b08dc892f3a467d20d920b",
        "session": "2vVCE",
        "bereich": "home",
        "item": "",
        "action": "enter",
        "value": "",
        "words": "0",
        "elementids": []
    },
    {
        "id": "186288",
        "time": "1766753969229",
        "appid": "46ae996145b08dc892f3a467d20d920b",
        "session": "2vVCE",
        "bereich": "zu-den-texten",
        "item": "",
        "action": "enter",
        "value": "",
        "words": "0",
        "elementids": []
    },
    {
        "id": "186289",
        "time": "1766754017174",
        "appid": "46ae996145b08dc892f3a467d20d920b",
        "session": "2vVCE",
        "bereich": "titelblatt_dieleidendesjungenwerthers",
        "item": "",
        "action": "enter",
        "value": "dieleidendesjungenwerthers",
        "words": "0",
        "elementids": []
    },
    {
        "id": "186290",
        "time": "1766754065114",
        "appid": "46ae996145b08dc892f3a467d20d920b",
        "session": "2vVCE",
        "bereich": "reader_dieleidendesjungenwerthers",
        "item": "",
        "action": "enter",
        "value": "dieleidendesjungenwerthers",
        "words": "0",
        "elementids": []
    },
    {
        "id": "186291",
        "time": "1766765991051",
        "appid": "4b44ff00cefbe0c65cd659f804b975d9",
        "session": "YIZYi",
        "bereich": "start",
        "item": "",
        "action": "enter",
        "value": "",
        "words": "0",
        "elementids": []
    },
    {
        "id": "186292",
        "time": "1766765996706",
        "appid": "4b44ff00cefbe0c65cd659f804b975d9",
        "session": "YIZYi",
        "bereich": "datenschutz-bestaetigen",
        "item": "",
        "action": "enter",
        "value": "",
        "words": "0",
        "elementids": []
    },
    {
        "id": "186293",
        "time": "1766765998431",
        "appid": "4b44ff00cefbe0c65cd659f804b975d9",
        "session": "YIZYi",
        "bereich": "fragebogen",
        "item": "",
        "action": "enter",
        "value": "",
        "words": "0",
        "elementids": []
    },
    {
        "id": "186294",
        "time": "1766766021980",
        "appid": "4b44ff00cefbe0c65cd659f804b975d9",
        "session": "YIZYi",
        "bereich": "home",
        "item": "",
        "action": "enter",
        "value": "",
        "words": "0",
        "elementids": []
    },
    {
        "id": "186295",
        "time": "1766766030368",
        "appid": "4b44ff00cefbe0c65cd659f804b975d9",
        "session": "YIZYi",
        "bereich": "zu-den-texten",
        "item": "",
        "action": "enter",
        "value": "",
        "words": "0",
        "elementids": []
    },
    {
        "id": "186296",
        "time": "1766766033700",
        "appid": "4b44ff00cefbe0c65cd659f804b975d9",
        "session": "YIZYi",
        "bereich": "titelblatt_antonreiser",
        "item": "",
        "action": "enter",
        "value": "antonreiser",
        "words": "0",
        "elementids": []
    },
    {
        "id": "186297",
        "time": "1766766038565",
        "appid": "4b44ff00cefbe0c65cd659f804b975d9",
        "session": "YIZYi",
        "bereich": "reader_antonreiser",
        "item": "",
        "action": "enter",
        "value": "antonreiser",
        "words": "0",
        "elementids": []
    },
    {
        "id": "186298",
        "time": "1766766079754",
        "appid": "4b44ff00cefbe0c65cd659f804b975d9",
        "session": "bxRtV",
        "bereich": "titelblatt_antonreiser",
        "item": "",
        "action": "enter",
        "value": "antonreiser",
        "words": "0",
        "elementids": []
    },
    {
        "id": "186299",
        "time": "1766766080354",
        "appid": "4b44ff00cefbe0c65cd659f804b975d9",
        "session": "bxRtV",
        "bereich": "zu-den-texten",
        "item": "",
        "action": "enter",
        "value": "",
        "words": "0",
        "elementids": []
    },
    {
        "id": "186300",
        "time": "1766766080896",
        "appid": "4b44ff00cefbe0c65cd659f804b975d9",
        "session": "bxRtV",
        "bereich": "home",
        "item": "",
        "action": "enter",
        "value": "",
        "words": "0",
        "elementids": []
    },
    {
        "id": "186301",
        "time": "1766766081507",
        "appid": "4b44ff00cefbe0c65cd659f804b975d9",
        "session": "bxRtV",
        "bereich": "fragebogen",
        "item": "",
        "action": "enter",
        "value": "",
        "words": "0",
        "elementids": []
    },
    {
        "id": "186302",
        "time": "1766766082120",
        "appid": "4b44ff00cefbe0c65cd659f804b975d9",
        "session": "bxRtV",
        "bereich": "datenschutz-bestaetigen",
        "item": "",
        "action": "enter",
        "value": "",
        "words": "0",
        "elementids": []
    },
    {
        "id": "186303",
        "time": "1766766083147",
        "appid": "4b44ff00cefbe0c65cd659f804b975d9",
        "session": "bxRtV",
        "bereich": "start",
        "item": "",
        "action": "enter",
        "value": "",
        "words": "0",
        "elementids": []
    },
    {
        "id": "186304",
        "time": "1766766083154",
        "appid": "4b44ff00cefbe0c65cd659f804b975d9",
        "session": "bxRtV",
        "bereich": "reader_antonreiser",
        "item": "",
        "action": "enter",
        "value": "antonreiser",
        "words": "0",
        "elementids": []
    },
    {
        "id": "186305",
        "time": "1766766083983",
        "appid": "4b44ff00cefbe0c65cd659f804b975d9",
        "session": "bxRtV",
        "bereich": "reader_antonreiser",
        "item": "page2",
        "action": "leave",
        "value": "0.0006",
        "words": "41",
        "elementids": [
            "antonreiser-0f372",
            "antonreiser-30e0d",
            "antonreiser-74984",
            "antonreiser-ccdd9",
            "antonreiser-d50bc",
            "antonreiser-df8dd",
            "antonreiser-f56bc",
            "antonreiser-f90d5"
        ]
    }
]