[
    {
        "id": "189385",
        "time": "1771512426550",
        "appid": "ae5ecbbbf04a3a3f392fdf1f3866e7d8",
        "session": "4NDvI",
        "bereich": "start",
        "item": "",
        "action": "enter",
        "value": "",
        "words": "0",
        "elementids": []
    },
    {
        "id": "189386",
        "time": "1771512430358",
        "appid": "ae5ecbbbf04a3a3f392fdf1f3866e7d8",
        "session": "4NDvI",
        "bereich": "datenschutz-bestaetigen",
        "item": "",
        "action": "enter",
        "value": "",
        "words": "0",
        "elementids": []
    },
    {
        "id": "189387",
        "time": "1771512996651",
        "appid": "c404ac8bec53012b09f5c45c04ebbdc7",
        "session": "fJMqX",
        "bereich": "start",
        "item": "",
        "action": "enter",
        "value": "",
        "words": "0",
        "elementids": []
    },
    {
        "id": "189388",
        "time": "1771512996666",
        "appid": "c404ac8bec53012b09f5c45c04ebbdc7",
        "session": "fJMqX",
        "bereich": "reader_buntesteine",
        "item": "",
        "action": "enter",
        "value": "buntesteine",
        "words": "0",
        "elementids": []
    },
    {
        "id": "189389",
        "time": "1771512997868",
        "appid": "c404ac8bec53012b09f5c45c04ebbdc7",
        "session": "fJMqX",
        "bereich": "reader_buntesteine",
        "item": "page143",
        "action": "enter",
        "value": "0.1364",
        "words": "107",
        "elementids": [
            "buntesteine-68e1d",
            "buntesteine-78707",
            "buntesteine-7c39f",
            "buntesteine-955af",
            "buntesteine-c1f76"
        ]
    },
    {
        "id": "189390",
        "time": "1771513000851",
        "appid": "c404ac8bec53012b09f5c45c04ebbdc7",
        "session": "fJMqX",
        "bereich": "reader_buntesteine",
        "item": "location",
        "action": "close",
        "value": "reject",
        "words": "0",
        "elementids": []
    },
    {
        "id": "189391",
        "time": "1771513003393",
        "appid": "c404ac8bec53012b09f5c45c04ebbdc7",
        "session": "fJMqX",
        "bereich": "home",
        "item": "",
        "action": "enter",
        "value": "",
        "words": "0",
        "elementids": []
    },
    {
        "id": "189392",
        "time": "1771513005393",
        "appid": "c404ac8bec53012b09f5c45c04ebbdc7",
        "session": "fJMqX",
        "bereich": "zu-den-texten",
        "item": "",
        "action": "enter",
        "value": "",
        "words": "0",
        "elementids": []
    },
    {
        "id": "189393",
        "time": "1771513039932",
        "appid": "c404ac8bec53012b09f5c45c04ebbdc7",
        "session": "ooj03",
        "bereich": "titelblatt_doncarlos",
        "item": "",
        "action": "enter",
        "value": "doncarlos",
        "words": "0",
        "elementids": []
    },
    {
        "id": "189394",
        "time": "1771513043865",
        "appid": "c404ac8bec53012b09f5c45c04ebbdc7",
        "session": "ooj03",
        "bereich": "warum-lesen-wir_doncarlos",
        "item": "",
        "action": "enter",
        "value": "doncarlos",
        "words": "0",
        "elementids": []
    },
    {
        "id": "189395",
        "time": "1771513164472",
        "appid": "c404ac8bec53012b09f5c45c04ebbdc7",
        "session": "ooj03",
        "bereich": "titelblatt_doncarlos",
        "item": "",
        "action": "enter",
        "value": "doncarlos",
        "words": "0",
        "elementids": []
    },
    {
        "id": "189396",
        "time": "1771513166072",
        "appid": "c404ac8bec53012b09f5c45c04ebbdc7",
        "session": "ooj03",
        "bereich": "zu-den-texten",
        "item": "",
        "action": "enter",
        "value": "",
        "words": "0",
        "elementids": []
    },
    {
        "id": "189397",
        "time": "1771513192737",
        "appid": "c404ac8bec53012b09f5c45c04ebbdc7",
        "session": "ooj03",
        "bereich": "titelblatt_doncarlos",
        "item": "",
        "action": "enter",
        "value": "doncarlos",
        "words": "0",
        "elementids": []
    },
    {
        "id": "189398",
        "time": "1771513194128",
        "appid": "c404ac8bec53012b09f5c45c04ebbdc7",
        "session": "ooj03",
        "bereich": "literaturmuseum_doncarlos",
        "item": "",
        "action": "enter",
        "value": "doncarlos",
        "words": "0",
        "elementids": []
    },
    {
        "id": "189399",
        "time": "1771513230323",
        "appid": "c404ac8bec53012b09f5c45c04ebbdc7",
        "session": "ooj03",
        "bereich": "titelblatt_doncarlos",
        "item": "",
        "action": "enter",
        "value": "doncarlos",
        "words": "0",
        "elementids": []
    },
    {
        "id": "189400",
        "time": "1771513232058",
        "appid": "c404ac8bec53012b09f5c45c04ebbdc7",
        "session": "ooj03",
        "bereich": "zu-den-texten",
        "item": "",
        "action": "enter",
        "value": "",
        "words": "0",
        "elementids": []
    },
    {
        "id": "189401",
        "time": "1771513236179",
        "appid": "c404ac8bec53012b09f5c45c04ebbdc7",
        "session": "ooj03",
        "bereich": "titelblatt_diemarquisevono",
        "item": "",
        "action": "enter",
        "value": "diemarquisevono",
        "words": "0",
        "elementids": []
    },
    {
        "id": "189402",
        "time": "1771513237428",
        "appid": "c404ac8bec53012b09f5c45c04ebbdc7",
        "session": "ooj03",
        "bereich": "literaturmuseum_diemarquisevono",
        "item": "",
        "action": "enter",
        "value": "diemarquisevono",
        "words": "0",
        "elementids": []
    },
    {
        "id": "189403",
        "time": "1771513239201",
        "appid": "c404ac8bec53012b09f5c45c04ebbdc7",
        "session": "ooj03",
        "bereich": "titelblatt_diemarquisevono",
        "item": "",
        "action": "enter",
        "value": "diemarquisevono",
        "words": "0",
        "elementids": []
    },
    {
        "id": "189404",
        "time": "1771513240057",
        "appid": "c404ac8bec53012b09f5c45c04ebbdc7",
        "session": "ooj03",
        "bereich": "warum-lesen-wir_diemarquisevono",
        "item": "",
        "action": "enter",
        "value": "diemarquisevono",
        "words": "0",
        "elementids": []
    },
    {
        "id": "189405",
        "time": "1771513248408",
        "appid": "c404ac8bec53012b09f5c45c04ebbdc7",
        "session": "ooj03",
        "bereich": "titelblatt_diemarquisevono",
        "item": "",
        "action": "enter",
        "value": "diemarquisevono",
        "words": "0",
        "elementids": []
    },
    {
        "id": "189406",
        "time": "1771513249544",
        "appid": "c404ac8bec53012b09f5c45c04ebbdc7",
        "session": "ooj03",
        "bereich": "zu-den-texten",
        "item": "",
        "action": "enter",
        "value": "",
        "words": "0",
        "elementids": []
    },
    {
        "id": "189407",
        "time": "1771513255363",
        "appid": "c404ac8bec53012b09f5c45c04ebbdc7",
        "session": "ooj03",
        "bereich": "titelblatt_fausti",
        "item": "",
        "action": "enter",
        "value": "fausti",
        "words": "0",
        "elementids": []
    },
    {
        "id": "189408",
        "time": "1771513256242",
        "appid": "c404ac8bec53012b09f5c45c04ebbdc7",
        "session": "ooj03",
        "bereich": "warum-lesen-wir_fausti",
        "item": "",
        "action": "enter",
        "value": "fausti",
        "words": "0",
        "elementids": []
    },
    {
        "id": "189409",
        "time": "1771513289054",
        "appid": "c404ac8bec53012b09f5c45c04ebbdc7",
        "session": "ooj03",
        "bereich": "titelblatt_fausti",
        "item": "",
        "action": "enter",
        "value": "fausti",
        "words": "0",
        "elementids": []
    },
    {
        "id": "189410",
        "time": "1771513290318",
        "appid": "c404ac8bec53012b09f5c45c04ebbdc7",
        "session": "ooj03",
        "bereich": "zu-den-texten",
        "item": "",
        "action": "enter",
        "value": "",
        "words": "0",
        "elementids": []
    },
    {
        "id": "189411",
        "time": "1771513306498",
        "appid": "c404ac8bec53012b09f5c45c04ebbdc7",
        "session": "ooj03",
        "bereich": "titelblatt_nathanderweise",
        "item": "",
        "action": "enter",
        "value": "nathanderweise",
        "words": "0",
        "elementids": []
    },
    {
        "id": "189412",
        "time": "1771513308322",
        "appid": "c404ac8bec53012b09f5c45c04ebbdc7",
        "session": "ooj03",
        "bereich": "warum-lesen-wir_nathanderweise",
        "item": "",
        "action": "enter",
        "value": "nathanderweise",
        "words": "0",
        "elementids": []
    },
    {
        "id": "189413",
        "time": "1771513343758",
        "appid": "c404ac8bec53012b09f5c45c04ebbdc7",
        "session": "ooj03",
        "bereich": "titelblatt_nathanderweise",
        "item": "",
        "action": "enter",
        "value": "nathanderweise",
        "words": "0",
        "elementids": []
    },
    {
        "id": "189414",
        "time": "1771513344859",
        "appid": "c404ac8bec53012b09f5c45c04ebbdc7",
        "session": "ooj03",
        "bereich": "zu-den-texten",
        "item": "",
        "action": "enter",
        "value": "",
        "words": "0",
        "elementids": []
    },
    {
        "id": "189415",
        "time": "1771513459527",
        "appid": "29c67a55d173ee9d9ef6522dd9a05cea",
        "session": "GIiKX",
        "bereich": "start",
        "item": "",
        "action": "enter",
        "value": "",
        "words": "0",
        "elementids": []
    },
    {
        "id": "189416",
        "time": "1771513466692",
        "appid": "29c67a55d173ee9d9ef6522dd9a05cea",
        "session": "GIiKX",
        "bereich": "datenschutz-bestaetigen",
        "item": "",
        "action": "enter",
        "value": "",
        "words": "0",
        "elementids": []
    },
    {
        "id": "189417",
        "time": "1771513469326",
        "appid": "29c67a55d173ee9d9ef6522dd9a05cea",
        "session": "GIiKX",
        "bereich": "fragebogen",
        "item": "",
        "action": "enter",
        "value": "",
        "words": "0",
        "elementids": []
    },
    {
        "id": "189418",
        "time": "1771513499285",
        "appid": "29c67a55d173ee9d9ef6522dd9a05cea",
        "session": "GIiKX",
        "bereich": "home",
        "item": "",
        "action": "enter",
        "value": "",
        "words": "0",
        "elementids": []
    },
    {
        "id": "189419",
        "time": "1771513514436",
        "appid": "29c67a55d173ee9d9ef6522dd9a05cea",
        "session": "GIiKX",
        "bereich": "zu-den-texten",
        "item": "",
        "action": "enter",
        "value": "",
        "words": "0",
        "elementids": []
    },
    {
        "id": "189420",
        "time": "1771513553191",
        "appid": "29c67a55d173ee9d9ef6522dd9a05cea",
        "session": "GIiKX",
        "bereich": "titelblatt_sonetteanorpheus",
        "item": "",
        "action": "enter",
        "value": "sonetteanorpheus",
        "words": "0",
        "elementids": []
    },
    {
        "id": "189421",
        "time": "1771513561757",
        "appid": "29c67a55d173ee9d9ef6522dd9a05cea",
        "session": "GIiKX",
        "bereich": "literaturmuseum_sonetteanorpheus",
        "item": "",
        "action": "enter",
        "value": "sonetteanorpheus",
        "words": "0",
        "elementids": []
    },
    {
        "id": "189422",
        "time": "1771513843109",
        "appid": "29c67a55d173ee9d9ef6522dd9a05cea",
        "session": "GIiKX",
        "bereich": "titelblatt_sonetteanorpheus",
        "item": "",
        "action": "enter",
        "value": "sonetteanorpheus",
        "words": "0",
        "elementids": []
    },
    {
        "id": "189423",
        "time": "1771513847609",
        "appid": "29c67a55d173ee9d9ef6522dd9a05cea",
        "session": "GIiKX",
        "bereich": "warum-lesen-wir_sonetteanorpheus",
        "item": "",
        "action": "enter",
        "value": "sonetteanorpheus",
        "words": "0",
        "elementids": []
    },
    {
        "id": "189424",
        "time": "1771513902036",
        "appid": "29c67a55d173ee9d9ef6522dd9a05cea",
        "session": "GIiKX",
        "bereich": "titelblatt_sonetteanorpheus",
        "item": "",
        "action": "enter",
        "value": "sonetteanorpheus",
        "words": "0",
        "elementids": []
    },
    {
        "id": "189425",
        "time": "1771513907928",
        "appid": "29c67a55d173ee9d9ef6522dd9a05cea",
        "session": "GIiKX",
        "bereich": "reader_sonetteanorpheus",
        "item": "",
        "action": "enter",
        "value": "sonetteanorpheus",
        "words": "0",
        "elementids": []
    },
    {
        "id": "189426",
        "time": "1771513961752",
        "appid": "29c67a55d173ee9d9ef6522dd9a05cea",
        "session": "GIiKX",
        "bereich": "reader_sonetteanorpheus",
        "item": "page2",
        "action": "enter",
        "value": "0.03",
        "words": "17",
        "elementids": [
            "sonetteanorpheus-5d721",
            "sonetteanorpheus-5ddf1",
            "sonetteanorpheus-bd459"
        ]
    },
    {
        "id": "189427",
        "time": "1771513962971",
        "appid": "29c67a55d173ee9d9ef6522dd9a05cea",
        "session": "GIiKX",
        "bereich": "reader_sonetteanorpheus",
        "item": "page3",
        "action": "enter",
        "value": "0.04",
        "words": "80",
        "elementids": [
            "sonetteanorpheus-09410",
            "sonetteanorpheus-0b41a",
            "sonetteanorpheus-11d21",
            "sonetteanorpheus-16400",
            "sonetteanorpheus-1daab",
            "sonetteanorpheus-27a6f",
            "sonetteanorpheus-2a091",
            "sonetteanorpheus-2aa2d",
            "sonetteanorpheus-2f5a3",
            "sonetteanorpheus-446b7",
            "sonetteanorpheus-6bdee",
            "sonetteanorpheus-a36f0",
            "sonetteanorpheus-abce9",
            "sonetteanorpheus-d5483",
            "sonetteanorpheus-db36c",
            "sonetteanorpheus-ee349",
            "sonetteanorpheus-efad6"
        ]
    },
    {
        "id": "189428",
        "time": "1771513970034",
        "appid": "29c67a55d173ee9d9ef6522dd9a05cea",
        "session": "GIiKX",
        "bereich": "reader_sonetteanorpheus",
        "item": "location",
        "action": "close",
        "value": "reject",
        "words": "0",
        "elementids": []
    },
    {
        "id": "189429",
        "time": "1771513971189",
        "appid": "29c67a55d173ee9d9ef6522dd9a05cea",
        "session": "GIiKX",
        "bereich": "reader_sonetteanorpheus",
        "item": "page2",
        "action": "enter",
        "value": "0.03",
        "words": "17",
        "elementids": [
            "sonetteanorpheus-5d721",
            "sonetteanorpheus-5ddf1",
            "sonetteanorpheus-bd459"
        ]
    },
    {
        "id": "189430",
        "time": "1771513973352",
        "appid": "29c67a55d173ee9d9ef6522dd9a05cea",
        "session": "GIiKX",
        "bereich": "reader_sonetteanorpheus",
        "item": "page1",
        "action": "enter",
        "value": "0.02",
        "words": "73",
        "elementids": [
            "sonetteanorpheus-2ebed",
            "sonetteanorpheus-40df0",
            "sonetteanorpheus-44d10",
            "sonetteanorpheus-4ad23",
            "sonetteanorpheus-6426c",
            "sonetteanorpheus-64373",
            "sonetteanorpheus-66584",
            "sonetteanorpheus-7a25c",
            "sonetteanorpheus-891c2",
            "sonetteanorpheus-92647",
            "sonetteanorpheus-98275",
            "sonetteanorpheus-9d089",
            "sonetteanorpheus-a0195",
            "sonetteanorpheus-c3d49",
            "sonetteanorpheus-cf376",
            "sonetteanorpheus-d3607",
            "sonetteanorpheus-ea68f",
            "sonetteanorpheus-ee6f4"
        ]
    },
    {
        "id": "189431",
        "time": "1771514026141",
        "appid": "29c67a55d173ee9d9ef6522dd9a05cea",
        "session": "GIiKX",
        "bereich": "second-menu",
        "item": "",
        "action": "enter",
        "value": "",
        "words": "0",
        "elementids": []
    },
    {
        "id": "189432",
        "time": "1771514041671",
        "appid": "29c67a55d173ee9d9ef6522dd9a05cea",
        "session": "GIiKX",
        "bereich": "schrifteinstellungen_sonetteanorpheus",
        "item": "",
        "action": "enter",
        "value": "sonetteanorpheus",
        "words": "0",
        "elementids": []
    },
    {
        "id": "189433",
        "time": "1771514170994",
        "appid": "29c67a55d173ee9d9ef6522dd9a05cea",
        "session": "pUxM4",
        "bereich": "second-menu",
        "item": "",
        "action": "enter",
        "value": "",
        "words": "0",
        "elementids": []
    },
    {
        "id": "189434",
        "time": "1771514176224",
        "appid": "29c67a55d173ee9d9ef6522dd9a05cea",
        "session": "pUxM4",
        "bereich": "warum-lesen-wir_sonetteanorpheus",
        "item": "",
        "action": "enter",
        "value": "sonetteanorpheus",
        "words": "0",
        "elementids": []
    },
    {
        "id": "189435",
        "time": "1771514208895",
        "appid": "29c67a55d173ee9d9ef6522dd9a05cea",
        "session": "pUxM4",
        "bereich": "second-menu",
        "item": "",
        "action": "enter",
        "value": "",
        "words": "0",
        "elementids": []
    },
    {
        "id": "189436",
        "time": "1771514214255",
        "appid": "29c67a55d173ee9d9ef6522dd9a05cea",
        "session": "pUxM4",
        "bereich": "literaturmuseum_sonetteanorpheus",
        "item": "",
        "action": "enter",
        "value": "sonetteanorpheus",
        "words": "0",
        "elementids": []
    },
    {
        "id": "189437",
        "time": "1771514291881",
        "appid": "29c67a55d173ee9d9ef6522dd9a05cea",
        "session": "i2IE4",
        "bereich": "second-menu",
        "item": "",
        "action": "enter",
        "value": "",
        "words": "0",
        "elementids": []
    },
    {
        "id": "189438",
        "time": "1771514300634",
        "appid": "29c67a55d173ee9d9ef6522dd9a05cea",
        "session": "i2IE4",
        "bereich": "reader_sonetteanorpheus",
        "item": "",
        "action": "enter",
        "value": "sonetteanorpheus",
        "words": "0",
        "elementids": []
    },
    {
        "id": "189439",
        "time": "1771514301355",
        "appid": "29c67a55d173ee9d9ef6522dd9a05cea",
        "session": "i2IE4",
        "bereich": "reader_sonetteanorpheus",
        "item": "page2",
        "action": "enter",
        "value": "0.0254",
        "words": "43",
        "elementids": [
            "sonetteanorpheus-2ebed",
            "sonetteanorpheus-44d10",
            "sonetteanorpheus-5d721",
            "sonetteanorpheus-5ddf1",
            "sonetteanorpheus-64373",
            "sonetteanorpheus-66584",
            "sonetteanorpheus-92647",
            "sonetteanorpheus-bd459",
            "sonetteanorpheus-ea68f"
        ]
    },
    {
        "id": "189440",
        "time": "1771514317046",
        "appid": "29c67a55d173ee9d9ef6522dd9a05cea",
        "session": "i2IE4",
        "bereich": "home",
        "item": "",
        "action": "enter",
        "value": "",
        "words": "0",
        "elementids": []
    },
    {
        "id": "189441",
        "time": "1771514322276",
        "appid": "29c67a55d173ee9d9ef6522dd9a05cea",
        "session": "i2IE4",
        "bereich": "zu-den-texten",
        "item": "",
        "action": "enter",
        "value": "",
        "words": "0",
        "elementids": []
    },
    {
        "id": "189442",
        "time": "1771514347765",
        "appid": "29c67a55d173ee9d9ef6522dd9a05cea",
        "session": "i2IE4",
        "bereich": "titelblatt_wallensteinslager",
        "item": "",
        "action": "enter",
        "value": "wallensteinslager",
        "words": "0",
        "elementids": []
    },
    {
        "id": "189443",
        "time": "1771514350254",
        "appid": "29c67a55d173ee9d9ef6522dd9a05cea",
        "session": "i2IE4",
        "bereich": "zu-den-texten",
        "item": "",
        "action": "enter",
        "value": "",
        "words": "0",
        "elementids": []
    },
    {
        "id": "189444",
        "time": "1771514363934",
        "appid": "29c67a55d173ee9d9ef6522dd9a05cea",
        "session": "i2IE4",
        "bereich": "titelblatt_sonetteanorpheus",
        "item": "",
        "action": "enter",
        "value": "sonetteanorpheus",
        "words": "0",
        "elementids": []
    },
    {
        "id": "189445",
        "time": "1771514371001",
        "appid": "29c67a55d173ee9d9ef6522dd9a05cea",
        "session": "i2IE4",
        "bereich": "reader_sonetteanorpheus",
        "item": "",
        "action": "enter",
        "value": "sonetteanorpheus",
        "words": "0",
        "elementids": []
    },
    {
        "id": "189446",
        "time": "1771514371770",
        "appid": "29c67a55d173ee9d9ef6522dd9a05cea",
        "session": "i2IE4",
        "bereich": "reader_sonetteanorpheus",
        "item": "page2",
        "action": "enter",
        "value": "0.0254",
        "words": "43",
        "elementids": [
            "sonetteanorpheus-2ebed",
            "sonetteanorpheus-44d10",
            "sonetteanorpheus-5d721",
            "sonetteanorpheus-5ddf1",
            "sonetteanorpheus-64373",
            "sonetteanorpheus-66584",
            "sonetteanorpheus-92647",
            "sonetteanorpheus-bd459",
            "sonetteanorpheus-ea68f"
        ]
    },
    {
        "id": "189447",
        "time": "1771514377088",
        "appid": "29c67a55d173ee9d9ef6522dd9a05cea",
        "session": "i2IE4",
        "bereich": "reader_sonetteanorpheus",
        "item": "page1",
        "action": "enter",
        "value": "0.0169",
        "words": "47",
        "elementids": [
            "sonetteanorpheus-40df0",
            "sonetteanorpheus-4ad23",
            "sonetteanorpheus-6426c",
            "sonetteanorpheus-7a25c",
            "sonetteanorpheus-891c2",
            "sonetteanorpheus-98275",
            "sonetteanorpheus-9d089",
            "sonetteanorpheus-a0195",
            "sonetteanorpheus-c3d49",
            "sonetteanorpheus-cf376",
            "sonetteanorpheus-d3607",
            "sonetteanorpheus-ee6f4"
        ]
    },
    {
        "id": "189448",
        "time": "1771514404932",
        "appid": "29c67a55d173ee9d9ef6522dd9a05cea",
        "session": "i2IE4",
        "bereich": "reader_sonetteanorpheus",
        "item": "page2",
        "action": "enter",
        "value": "0.0254",
        "words": "43",
        "elementids": [
            "sonetteanorpheus-2ebed",
            "sonetteanorpheus-44d10",
            "sonetteanorpheus-5d721",
            "sonetteanorpheus-5ddf1",
            "sonetteanorpheus-64373",
            "sonetteanorpheus-66584",
            "sonetteanorpheus-92647",
            "sonetteanorpheus-bd459",
            "sonetteanorpheus-ea68f"
        ]
    },
    {
        "id": "189449",
        "time": "1771514423594",
        "appid": "29c67a55d173ee9d9ef6522dd9a05cea",
        "session": "i2IE4",
        "bereich": "reader_sonetteanorpheus",
        "item": "page3",
        "action": "enter",
        "value": "0.0339",
        "words": "51",
        "elementids": [
            "sonetteanorpheus-09410",
            "sonetteanorpheus-0b41a",
            "sonetteanorpheus-16400",
            "sonetteanorpheus-2a091",
            "sonetteanorpheus-2f5a3",
            "sonetteanorpheus-6bdee",
            "sonetteanorpheus-abce9",
            "sonetteanorpheus-d5483",
            "sonetteanorpheus-db36c",
            "sonetteanorpheus-efad6"
        ]
    },
    {
        "id": "189450",
        "time": "1771514445996",
        "appid": "29c67a55d173ee9d9ef6522dd9a05cea",
        "session": "i2IE4",
        "bereich": "reader_sonetteanorpheus",
        "item": "page4",
        "action": "enter",
        "value": "0.0424",
        "words": "47",
        "elementids": [
            "sonetteanorpheus-0c5a4",
            "sonetteanorpheus-11d21",
            "sonetteanorpheus-1daab",
            "sonetteanorpheus-224de",
            "sonetteanorpheus-27a6f",
            "sonetteanorpheus-2aa2d",
            "sonetteanorpheus-446b7",
            "sonetteanorpheus-a36f0",
            "sonetteanorpheus-a654b",
            "sonetteanorpheus-bcf98",
            "sonetteanorpheus-ca33d",
            "sonetteanorpheus-ee349"
        ]
    },
    {
        "id": "189451",
        "time": "1771514450959",
        "appid": "29c67a55d173ee9d9ef6522dd9a05cea",
        "session": "i2IE4",
        "bereich": "reader_sonetteanorpheus",
        "item": "page5",
        "action": "enter",
        "value": "0.0508",
        "words": "54",
        "elementids": [
            "sonetteanorpheus-05f20",
            "sonetteanorpheus-14d3f",
            "sonetteanorpheus-23a00",
            "sonetteanorpheus-49af1",
            "sonetteanorpheus-4d091",
            "sonetteanorpheus-55cc3",
            "sonetteanorpheus-601bc",
            "sonetteanorpheus-6dd2c",
            "sonetteanorpheus-9680f",
            "sonetteanorpheus-99ad2",
            "sonetteanorpheus-afb13",
            "sonetteanorpheus-b9c8b",
            "sonetteanorpheus-d1b13",
            "sonetteanorpheus-d5f12",
            "sonetteanorpheus-df236",
            "sonetteanorpheus-eb4f7"
        ]
    },
    {
        "id": "189452",
        "time": "1771514451872",
        "appid": "29c67a55d173ee9d9ef6522dd9a05cea",
        "session": "i2IE4",
        "bereich": "reader_sonetteanorpheus",
        "item": "page6",
        "action": "enter",
        "value": "0.0593",
        "words": "44",
        "elementids": [
            "sonetteanorpheus-01d28",
            "sonetteanorpheus-0d2d0",
            "sonetteanorpheus-45eaa",
            "sonetteanorpheus-53797",
            "sonetteanorpheus-55e62",
            "sonetteanorpheus-5f221",
            "sonetteanorpheus-64fe7",
            "sonetteanorpheus-6e2a6",
            "sonetteanorpheus-8c237",
            "sonetteanorpheus-968fa",
            "sonetteanorpheus-a45b7"
        ]
    },
    {
        "id": "189453",
        "time": "1771514452379",
        "appid": "29c67a55d173ee9d9ef6522dd9a05cea",
        "session": "i2IE4",
        "bereich": "reader_sonetteanorpheus",
        "item": "page7",
        "action": "enter",
        "value": "0.0678",
        "words": "47",
        "elementids": [
            "sonetteanorpheus-025e8",
            "sonetteanorpheus-234a8",
            "sonetteanorpheus-57cd8",
            "sonetteanorpheus-87acb",
            "sonetteanorpheus-9b137",
            "sonetteanorpheus-a0604",
            "sonetteanorpheus-c1d57",
            "sonetteanorpheus-da34c",
            "sonetteanorpheus-e7204",
            "sonetteanorpheus-f8c30"
        ]
    },
    {
        "id": "189454",
        "time": "1771514453493",
        "appid": "29c67a55d173ee9d9ef6522dd9a05cea",
        "session": "i2IE4",
        "bereich": "reader_sonetteanorpheus",
        "item": "page8",
        "action": "enter",
        "value": "0.0763",
        "words": "35",
        "elementids": [
            "sonetteanorpheus-3a6e8",
            "sonetteanorpheus-63bc6",
            "sonetteanorpheus-79d88",
            "sonetteanorpheus-87acb",
            "sonetteanorpheus-a38e6",
            "sonetteanorpheus-c2dd3",
            "sonetteanorpheus-c90e6"
        ]
    },
    {
        "id": "189455",
        "time": "1771514454072",
        "appid": "29c67a55d173ee9d9ef6522dd9a05cea",
        "session": "i2IE4",
        "bereich": "reader_sonetteanorpheus",
        "item": "page9",
        "action": "enter",
        "value": "0.0847",
        "words": "50",
        "elementids": [
            "sonetteanorpheus-04014",
            "sonetteanorpheus-09a26",
            "sonetteanorpheus-23ca4",
            "sonetteanorpheus-259f9",
            "sonetteanorpheus-3edb5",
            "sonetteanorpheus-4e8f4",
            "sonetteanorpheus-572eb",
            "sonetteanorpheus-6faa6",
            "sonetteanorpheus-8175d",
            "sonetteanorpheus-91173",
            "sonetteanorpheus-a382a",
            "sonetteanorpheus-b17ed",
            "sonetteanorpheus-cd2df",
            "sonetteanorpheus-f69b4"
        ]
    },
    {
        "id": "189456",
        "time": "1771514454551",
        "appid": "29c67a55d173ee9d9ef6522dd9a05cea",
        "session": "i2IE4",
        "bereich": "reader_sonetteanorpheus",
        "item": "page10",
        "action": "enter",
        "value": "0.0932",
        "words": "40",
        "elementids": [
            "sonetteanorpheus-0b834",
            "sonetteanorpheus-1a032",
            "sonetteanorpheus-21081",
            "sonetteanorpheus-5d55c",
            "sonetteanorpheus-a4e9f",
            "sonetteanorpheus-c4da2"
        ]
    },
    {
        "id": "189457",
        "time": "1771514455006",
        "appid": "29c67a55d173ee9d9ef6522dd9a05cea",
        "session": "i2IE4",
        "bereich": "reader_sonetteanorpheus",
        "item": "page11",
        "action": "enter",
        "value": "0.1017",
        "words": "45",
        "elementids": [
            "sonetteanorpheus-1b646",
            "sonetteanorpheus-208b8",
            "sonetteanorpheus-24329",
            "sonetteanorpheus-7a592",
            "sonetteanorpheus-83dcd",
            "sonetteanorpheus-8f85b",
            "sonetteanorpheus-90fe2",
            "sonetteanorpheus-b0dab",
            "sonetteanorpheus-bf738",
            "sonetteanorpheus-d714c"
        ]
    },
    {
        "id": "189458",
        "time": "1771514455335",
        "appid": "29c67a55d173ee9d9ef6522dd9a05cea",
        "session": "i2IE4",
        "bereich": "reader_sonetteanorpheus",
        "item": "page12",
        "action": "enter",
        "value": "0.1102",
        "words": "36",
        "elementids": [
            "sonetteanorpheus-02a95",
            "sonetteanorpheus-0f1b0",
            "sonetteanorpheus-31c5f",
            "sonetteanorpheus-6b693",
            "sonetteanorpheus-dcc0f",
            "sonetteanorpheus-ff2b6"
        ]
    },
    {
        "id": "189459",
        "time": "1771514455681",
        "appid": "29c67a55d173ee9d9ef6522dd9a05cea",
        "session": "i2IE4",
        "bereich": "reader_sonetteanorpheus",
        "item": "page13",
        "action": "enter",
        "value": "0.1186",
        "words": "44",
        "elementids": [
            "sonetteanorpheus-0319b",
            "sonetteanorpheus-0484e",
            "sonetteanorpheus-229c1",
            "sonetteanorpheus-25507",
            "sonetteanorpheus-4cfc9",
            "sonetteanorpheus-60f8b",
            "sonetteanorpheus-865ab",
            "sonetteanorpheus-9224b",
            "sonetteanorpheus-95abb",
            "sonetteanorpheus-dd6f9",
            "sonetteanorpheus-ed6ad"
        ]
    },
    {
        "id": "189460",
        "time": "1771514456048",
        "appid": "29c67a55d173ee9d9ef6522dd9a05cea",
        "session": "i2IE4",
        "bereich": "reader_sonetteanorpheus",
        "item": "page14",
        "action": "enter",
        "value": "0.1271",
        "words": "34",
        "elementids": [
            "sonetteanorpheus-3867f",
            "sonetteanorpheus-60f64",
            "sonetteanorpheus-72324",
            "sonetteanorpheus-81a67",
            "sonetteanorpheus-86109",
            "sonetteanorpheus-c3682"
        ]
    },
    {
        "id": "189461",
        "time": "1771514456670",
        "appid": "29c67a55d173ee9d9ef6522dd9a05cea",
        "session": "i2IE4",
        "bereich": "reader_sonetteanorpheus",
        "item": "page15",
        "action": "enter",
        "value": "0.1356",
        "words": "44",
        "elementids": [
            "sonetteanorpheus-135a3",
            "sonetteanorpheus-29f0b",
            "sonetteanorpheus-30fc9",
            "sonetteanorpheus-3e9f2",
            "sonetteanorpheus-8c2d5",
            "sonetteanorpheus-a3e15",
            "sonetteanorpheus-b4f29",
            "sonetteanorpheus-f151b",
            "sonetteanorpheus-f1df6",
            "sonetteanorpheus-fc2e4"
        ]
    },
    {
        "id": "189462",
        "time": "1771514457052",
        "appid": "29c67a55d173ee9d9ef6522dd9a05cea",
        "session": "i2IE4",
        "bereich": "reader_sonetteanorpheus",
        "item": "page16",
        "action": "enter",
        "value": "0.1441",
        "words": "34",
        "elementids": [
            "sonetteanorpheus-37fa8",
            "sonetteanorpheus-39793",
            "sonetteanorpheus-7ba37",
            "sonetteanorpheus-99f07",
            "sonetteanorpheus-a3a70",
            "sonetteanorpheus-edf0b",
            "sonetteanorpheus-ef4cc",
            "sonetteanorpheus-f19ad"
        ]
    },
    {
        "id": "189463",
        "time": "1771514457535",
        "appid": "29c67a55d173ee9d9ef6522dd9a05cea",
        "session": "i2IE4",
        "bereich": "reader_sonetteanorpheus",
        "item": "page17",
        "action": "enter",
        "value": "0.1525",
        "words": "39",
        "elementids": [
            "sonetteanorpheus-02ae4",
            "sonetteanorpheus-0a0f4",
            "sonetteanorpheus-0f0e3",
            "sonetteanorpheus-259f3",
            "sonetteanorpheus-2db58",
            "sonetteanorpheus-45d3e",
            "sonetteanorpheus-6786b",
            "sonetteanorpheus-ac60f",
            "sonetteanorpheus-b2462",
            "sonetteanorpheus-b3d50",
            "sonetteanorpheus-b5e90",
            "sonetteanorpheus-caaaa",
            "sonetteanorpheus-caee4",
            "sonetteanorpheus-fe67d"
        ]
    },
    {
        "id": "189464",
        "time": "1771514464468",
        "appid": "29c67a55d173ee9d9ef6522dd9a05cea",
        "session": "i2IE4",
        "bereich": "reader_sonetteanorpheus",
        "item": "emotion",
        "action": "close",
        "value": "reject",
        "words": "0",
        "elementids": []
    },
    {
        "id": "189465",
        "time": "1771514466426",
        "appid": "29c67a55d173ee9d9ef6522dd9a05cea",
        "session": "i2IE4",
        "bereich": "reader_sonetteanorpheus",
        "item": "page18",
        "action": "enter",
        "value": "0.161",
        "words": "3",
        "elementids": [
            "sonetteanorpheus-1c627"
        ]
    },
    {
        "id": "189466",
        "time": "1771514467071",
        "appid": "29c67a55d173ee9d9ef6522dd9a05cea",
        "session": "i2IE4",
        "bereich": "reader_sonetteanorpheus",
        "item": "page19",
        "action": "enter",
        "value": "0.1695",
        "words": "37",
        "elementids": [
            "sonetteanorpheus-1be57",
            "sonetteanorpheus-1f976",
            "sonetteanorpheus-23b1a",
            "sonetteanorpheus-3cd67",
            "sonetteanorpheus-4b078",
            "sonetteanorpheus-73955",
            "sonetteanorpheus-d7c32",
            "sonetteanorpheus-e1dbf",
            "sonetteanorpheus-ea71f"
        ]
    },
    {
        "id": "189467",
        "time": "1771514467947",
        "appid": "29c67a55d173ee9d9ef6522dd9a05cea",
        "session": "i2IE4",
        "bereich": "reader_sonetteanorpheus",
        "item": "page20",
        "action": "enter",
        "value": "0.178",
        "words": "27",
        "elementids": [
            "sonetteanorpheus-06f6f",
            "sonetteanorpheus-41bf3",
            "sonetteanorpheus-465c8",
            "sonetteanorpheus-7c4cb",
            "sonetteanorpheus-93002",
            "sonetteanorpheus-e3b3f"
        ]
    },
    {
        "id": "189468",
        "time": "1771514468455",
        "appid": "29c67a55d173ee9d9ef6522dd9a05cea",
        "session": "i2IE4",
        "bereich": "reader_sonetteanorpheus",
        "item": "page21",
        "action": "enter",
        "value": "0.1864",
        "words": "48",
        "elementids": [
            "sonetteanorpheus-192f1",
            "sonetteanorpheus-1e0a9",
            "sonetteanorpheus-3252d",
            "sonetteanorpheus-3427b",
            "sonetteanorpheus-38fd9",
            "sonetteanorpheus-65e06",
            "sonetteanorpheus-aa3e7",
            "sonetteanorpheus-b9208",
            "sonetteanorpheus-c0d89",
            "sonetteanorpheus-d2798",
            "sonetteanorpheus-d6534",
            "sonetteanorpheus-d6726",
            "sonetteanorpheus-e69a6"
        ]
    },
    {
        "id": "189469",
        "time": "1771514468899",
        "appid": "29c67a55d173ee9d9ef6522dd9a05cea",
        "session": "i2IE4",
        "bereich": "reader_sonetteanorpheus",
        "item": "page22",
        "action": "enter",
        "value": "0.1949",
        "words": "32",
        "elementids": [
            "sonetteanorpheus-112f8",
            "sonetteanorpheus-31bb7",
            "sonetteanorpheus-78896",
            "sonetteanorpheus-7e59f",
            "sonetteanorpheus-7e9ec",
            "sonetteanorpheus-875cd",
            "sonetteanorpheus-c33f8",
            "sonetteanorpheus-d9b7a",
            "sonetteanorpheus-fc9d2",
            "sonetteanorpheus-fde4f"
        ]
    },
    {
        "id": "189470",
        "time": "1771514469443",
        "appid": "29c67a55d173ee9d9ef6522dd9a05cea",
        "session": "i2IE4",
        "bereich": "reader_sonetteanorpheus",
        "item": "page23",
        "action": "enter",
        "value": "0.2034",
        "words": "43",
        "elementids": [
            "sonetteanorpheus-10232",
            "sonetteanorpheus-27256",
            "sonetteanorpheus-40156",
            "sonetteanorpheus-4cb47",
            "sonetteanorpheus-4de7b",
            "sonetteanorpheus-506b2",
            "sonetteanorpheus-a75b0",
            "sonetteanorpheus-b84b6",
            "sonetteanorpheus-bb16f",
            "sonetteanorpheus-e40ad",
            "sonetteanorpheus-f5c67"
        ]
    },
    {
        "id": "189471",
        "time": "1771514470255",
        "appid": "29c67a55d173ee9d9ef6522dd9a05cea",
        "session": "i2IE4",
        "bereich": "reader_sonetteanorpheus",
        "item": "page24",
        "action": "enter",
        "value": "0.2119",
        "words": "29",
        "elementids": [
            "sonetteanorpheus-092ff",
            "sonetteanorpheus-1fc7f",
            "sonetteanorpheus-801ba",
            "sonetteanorpheus-b84b6",
            "sonetteanorpheus-c3fed",
            "sonetteanorpheus-deb1a",
            "sonetteanorpheus-ecd5e",
            "sonetteanorpheus-f1bfb"
        ]
    },
    {
        "id": "189472",
        "time": "1771514470701",
        "appid": "29c67a55d173ee9d9ef6522dd9a05cea",
        "session": "i2IE4",
        "bereich": "reader_sonetteanorpheus",
        "item": "page25",
        "action": "enter",
        "value": "0.2203",
        "words": "41",
        "elementids": [
            "sonetteanorpheus-1007c",
            "sonetteanorpheus-30a54",
            "sonetteanorpheus-5f773",
            "sonetteanorpheus-63cc4",
            "sonetteanorpheus-72f3f",
            "sonetteanorpheus-971b4",
            "sonetteanorpheus-c0051",
            "sonetteanorpheus-c85a3",
            "sonetteanorpheus-cbdb7",
            "sonetteanorpheus-cf518",
            "sonetteanorpheus-e2622",
            "sonetteanorpheus-e89c9"
        ]
    },
    {
        "id": "189473",
        "time": "1771514471086",
        "appid": "29c67a55d173ee9d9ef6522dd9a05cea",
        "session": "i2IE4",
        "bereich": "reader_sonetteanorpheus",
        "item": "page26",
        "action": "enter",
        "value": "0.2288",
        "words": "30",
        "elementids": [
            "sonetteanorpheus-1b56b",
            "sonetteanorpheus-2262d",
            "sonetteanorpheus-430e9",
            "sonetteanorpheus-71f82",
            "sonetteanorpheus-932a2",
            "sonetteanorpheus-c348e"
        ]
    },
    {
        "id": "189474",
        "time": "1771514471447",
        "appid": "29c67a55d173ee9d9ef6522dd9a05cea",
        "session": "i2IE4",
        "bereich": "reader_sonetteanorpheus",
        "item": "page27",
        "action": "enter",
        "value": "0.2373",
        "words": "51",
        "elementids": [
            "sonetteanorpheus-0d85e",
            "sonetteanorpheus-1904a",
            "sonetteanorpheus-23bd2",
            "sonetteanorpheus-49525",
            "sonetteanorpheus-827b9",
            "sonetteanorpheus-c7162",
            "sonetteanorpheus-c970e",
            "sonetteanorpheus-d3ae9",
            "sonetteanorpheus-f7f84"
        ]
    },
    {
        "id": "189475",
        "time": "1771514471797",
        "appid": "29c67a55d173ee9d9ef6522dd9a05cea",
        "session": "i2IE4",
        "bereich": "reader_sonetteanorpheus",
        "item": "page28",
        "action": "enter",
        "value": "0.2458",
        "words": "40",
        "elementids": [
            "sonetteanorpheus-05dd8",
            "sonetteanorpheus-2f0a7",
            "sonetteanorpheus-3949c",
            "sonetteanorpheus-60ff6",
            "sonetteanorpheus-6f00d",
            "sonetteanorpheus-7f36c",
            "sonetteanorpheus-99d8e",
            "sonetteanorpheus-da0ad"
        ]
    },
    {
        "id": "189476",
        "time": "1771514473073",
        "appid": "29c67a55d173ee9d9ef6522dd9a05cea",
        "session": "i2IE4",
        "bereich": "reader_sonetteanorpheus",
        "item": "page29",
        "action": "enter",
        "value": "0.2542",
        "words": "50",
        "elementids": [
            "sonetteanorpheus-00348",
            "sonetteanorpheus-0c537",
            "sonetteanorpheus-17b23",
            "sonetteanorpheus-66b5d",
            "sonetteanorpheus-68cc8",
            "sonetteanorpheus-77018",
            "sonetteanorpheus-90adb",
            "sonetteanorpheus-9cedd",
            "sonetteanorpheus-acad6",
            "sonetteanorpheus-cc3fd",
            "sonetteanorpheus-d030e",
            "sonetteanorpheus-e15b1",
            "sonetteanorpheus-f9b0c"
        ]
    },
    {
        "id": "189477",
        "time": "1771514473623",
        "appid": "29c67a55d173ee9d9ef6522dd9a05cea",
        "session": "i2IE4",
        "bereich": "reader_sonetteanorpheus",
        "item": "page30",
        "action": "enter",
        "value": "0.2627",
        "words": "34",
        "elementids": [
            "sonetteanorpheus-2dde1",
            "sonetteanorpheus-36673",
            "sonetteanorpheus-74300",
            "sonetteanorpheus-810a5",
            "sonetteanorpheus-ad037",
            "sonetteanorpheus-b171e",
            "sonetteanorpheus-bf1ee",
            "sonetteanorpheus-bf62f",
            "sonetteanorpheus-cd993"
        ]
    },
    {
        "id": "189478",
        "time": "1771514474294",
        "appid": "29c67a55d173ee9d9ef6522dd9a05cea",
        "session": "i2IE4",
        "bereich": "reader_sonetteanorpheus",
        "item": "page31",
        "action": "enter",
        "value": "0.2712",
        "words": "44",
        "elementids": [
            "sonetteanorpheus-03ba1",
            "sonetteanorpheus-09f36",
            "sonetteanorpheus-0cff9",
            "sonetteanorpheus-11d77",
            "sonetteanorpheus-1a6ce",
            "sonetteanorpheus-75409",
            "sonetteanorpheus-815d9",
            "sonetteanorpheus-91570",
            "sonetteanorpheus-9282e",
            "sonetteanorpheus-93553",
            "sonetteanorpheus-c8ae3",
            "sonetteanorpheus-d6eba"
        ]
    },
    {
        "id": "189479",
        "time": "1771514474898",
        "appid": "29c67a55d173ee9d9ef6522dd9a05cea",
        "session": "i2IE4",
        "bereich": "reader_sonetteanorpheus",
        "item": "page32",
        "action": "enter",
        "value": "0.2797",
        "words": "42",
        "elementids": [
            "sonetteanorpheus-2fef9",
            "sonetteanorpheus-40c01",
            "sonetteanorpheus-47bf2",
            "sonetteanorpheus-705b8",
            "sonetteanorpheus-7ed7e",
            "sonetteanorpheus-91f0e",
            "sonetteanorpheus-cd353",
            "sonetteanorpheus-d8c15",
            "sonetteanorpheus-e5534",
            "sonetteanorpheus-f0045",
            "sonetteanorpheus-fe65e"
        ]
    },
    {
        "id": "189480",
        "time": "1771514475394",
        "appid": "29c67a55d173ee9d9ef6522dd9a05cea",
        "session": "i2IE4",
        "bereich": "reader_sonetteanorpheus",
        "item": "page33",
        "action": "enter",
        "value": "0.2881",
        "words": "74",
        "elementids": [
            "sonetteanorpheus-1000f",
            "sonetteanorpheus-4e9e1",
            "sonetteanorpheus-aa3ff",
            "sonetteanorpheus-c54b1"
        ]
    },
    {
        "id": "189481",
        "time": "1771514475698",
        "appid": "29c67a55d173ee9d9ef6522dd9a05cea",
        "session": "i2IE4",
        "bereich": "reader_sonetteanorpheus",
        "item": "page34",
        "action": "enter",
        "value": "0.2966",
        "words": "35",
        "elementids": [
            "sonetteanorpheus-2353d",
            "sonetteanorpheus-3091c",
            "sonetteanorpheus-3d8bb",
            "sonetteanorpheus-50e99",
            "sonetteanorpheus-51b1d",
            "sonetteanorpheus-777ab",
            "sonetteanorpheus-78f3d",
            "sonetteanorpheus-83153",
            "sonetteanorpheus-8389d",
            "sonetteanorpheus-84081",
            "sonetteanorpheus-8f35e",
            "sonetteanorpheus-a9bf5",
            "sonetteanorpheus-aaf62",
            "sonetteanorpheus-bc45c",
            "sonetteanorpheus-c8251",
            "sonetteanorpheus-ee27e"
        ]
    },
    {
        "id": "189482",
        "time": "1771514477077",
        "appid": "29c67a55d173ee9d9ef6522dd9a05cea",
        "session": "i2IE4",
        "bereich": "reader_sonetteanorpheus",
        "item": "page33",
        "action": "enter",
        "value": "0.2881",
        "words": "74",
        "elementids": [
            "sonetteanorpheus-1000f",
            "sonetteanorpheus-4e9e1",
            "sonetteanorpheus-aa3ff",
            "sonetteanorpheus-c54b1"
        ]
    },
    {
        "id": "189483",
        "time": "1771514489961",
        "appid": "29c67a55d173ee9d9ef6522dd9a05cea",
        "session": "i2IE4",
        "bereich": "reader_sonetteanorpheus",
        "item": "page34",
        "action": "enter",
        "value": "0.2966",
        "words": "35",
        "elementids": [
            "sonetteanorpheus-2353d",
            "sonetteanorpheus-3091c",
            "sonetteanorpheus-3d8bb",
            "sonetteanorpheus-50e99",
            "sonetteanorpheus-51b1d",
            "sonetteanorpheus-777ab",
            "sonetteanorpheus-78f3d",
            "sonetteanorpheus-83153",
            "sonetteanorpheus-8389d",
            "sonetteanorpheus-84081",
            "sonetteanorpheus-8f35e",
            "sonetteanorpheus-a9bf5",
            "sonetteanorpheus-aaf62",
            "sonetteanorpheus-bc45c",
            "sonetteanorpheus-c8251",
            "sonetteanorpheus-ee27e"
        ]
    },
    {
        "id": "189484",
        "time": "1771514492143",
        "appid": "29c67a55d173ee9d9ef6522dd9a05cea",
        "session": "i2IE4",
        "bereich": "reader_sonetteanorpheus",
        "item": "page35",
        "action": "enter",
        "value": "0.3051",
        "words": "4",
        "elementids": [
            "sonetteanorpheus-e8773"
        ]
    },
    {
        "id": "189485",
        "time": "1771514493727",
        "appid": "29c67a55d173ee9d9ef6522dd9a05cea",
        "session": "i2IE4",
        "bereich": "reader_sonetteanorpheus",
        "item": "page36",
        "action": "enter",
        "value": "0.3136",
        "words": "39",
        "elementids": [
            "sonetteanorpheus-2d184",
            "sonetteanorpheus-339ab",
            "sonetteanorpheus-44164",
            "sonetteanorpheus-4f1d7",
            "sonetteanorpheus-69b7f",
            "sonetteanorpheus-69d77",
            "sonetteanorpheus-7fbe4",
            "sonetteanorpheus-81424",
            "sonetteanorpheus-9ac71",
            "sonetteanorpheus-aa68d",
            "sonetteanorpheus-b4f40",
            "sonetteanorpheus-bd43b",
            "sonetteanorpheus-c2bc2",
            "sonetteanorpheus-fc00f"
        ]
    },
    {
        "id": "189486",
        "time": "1771514494760",
        "appid": "29c67a55d173ee9d9ef6522dd9a05cea",
        "session": "i2IE4",
        "bereich": "reader_sonetteanorpheus",
        "item": "page37",
        "action": "enter",
        "value": "0.322",
        "words": "3",
        "elementids": [
            "sonetteanorpheus-e29dc"
        ]
    },
    {
        "id": "189487",
        "time": "1771514495709",
        "appid": "29c67a55d173ee9d9ef6522dd9a05cea",
        "session": "i2IE4",
        "bereich": "reader_sonetteanorpheus",
        "item": "page38",
        "action": "enter",
        "value": "0.3305",
        "words": "38",
        "elementids": [
            "sonetteanorpheus-09834",
            "sonetteanorpheus-192d5",
            "sonetteanorpheus-36751",
            "sonetteanorpheus-3a3f0",
            "sonetteanorpheus-5c57e",
            "sonetteanorpheus-9687e",
            "sonetteanorpheus-a74a4",
            "sonetteanorpheus-a7cdf",
            "sonetteanorpheus-b42a2",
            "sonetteanorpheus-b6f1b",
            "sonetteanorpheus-ba7de",
            "sonetteanorpheus-c38d8",
            "sonetteanorpheus-e2fa6"
        ]
    },
    {
        "id": "189488",
        "time": "1771514496143",
        "appid": "29c67a55d173ee9d9ef6522dd9a05cea",
        "session": "i2IE4",
        "bereich": "reader_sonetteanorpheus",
        "item": "page39",
        "action": "enter",
        "value": "0.339",
        "words": "7",
        "elementids": [
            "sonetteanorpheus-2238b",
            "sonetteanorpheus-294a8"
        ]
    },
    {
        "id": "189489",
        "time": "1771514496410",
        "appid": "29c67a55d173ee9d9ef6522dd9a05cea",
        "session": "i2IE4",
        "bereich": "reader_sonetteanorpheus",
        "item": "page40",
        "action": "enter",
        "value": "0.3475",
        "words": "48",
        "elementids": [
            "sonetteanorpheus-0321a",
            "sonetteanorpheus-10fb4",
            "sonetteanorpheus-170f9",
            "sonetteanorpheus-25c47",
            "sonetteanorpheus-44ac6",
            "sonetteanorpheus-5f515",
            "sonetteanorpheus-653ae",
            "sonetteanorpheus-7024b",
            "sonetteanorpheus-c6533",
            "sonetteanorpheus-e39e2"
        ]
    },
    {
        "id": "189490",
        "time": "1771514496643",
        "appid": "29c67a55d173ee9d9ef6522dd9a05cea",
        "session": "i2IE4",
        "bereich": "reader_sonetteanorpheus",
        "item": "page41",
        "action": "enter",
        "value": "0.3559",
        "words": "34",
        "elementids": [
            "sonetteanorpheus-0013b",
            "sonetteanorpheus-5f7c7",
            "sonetteanorpheus-6e5c9",
            "sonetteanorpheus-71439",
            "sonetteanorpheus-74bff",
            "sonetteanorpheus-b2e61",
            "sonetteanorpheus-b7c53",
            "sonetteanorpheus-f6787",
            "sonetteanorpheus-fd1b2"
        ]
    },
    {
        "id": "189491",
        "time": "1771514496809",
        "appid": "29c67a55d173ee9d9ef6522dd9a05cea",
        "session": "i2IE4",
        "bereich": "reader_sonetteanorpheus",
        "item": "page42",
        "action": "enter",
        "value": "0.3644",
        "words": "45",
        "elementids": [
            "sonetteanorpheus-08805",
            "sonetteanorpheus-0908b",
            "sonetteanorpheus-0b1f3",
            "sonetteanorpheus-7209b",
            "sonetteanorpheus-99d0a",
            "sonetteanorpheus-bfd35",
            "sonetteanorpheus-dbaae",
            "sonetteanorpheus-e7f6f",
            "sonetteanorpheus-eb62f",
            "sonetteanorpheus-f53f5",
            "sonetteanorpheus-fb988",
            "sonetteanorpheus-fcb5f"
        ]
    },
    {
        "id": "189492",
        "time": "1771514497025",
        "appid": "29c67a55d173ee9d9ef6522dd9a05cea",
        "session": "i2IE4",
        "bereich": "reader_sonetteanorpheus",
        "item": "page43",
        "action": "enter",
        "value": "0.3729",
        "words": "37",
        "elementids": [
            "sonetteanorpheus-0510b",
            "sonetteanorpheus-18536",
            "sonetteanorpheus-63ba1",
            "sonetteanorpheus-709f0",
            "sonetteanorpheus-776f7",
            "sonetteanorpheus-87bb9",
            "sonetteanorpheus-88142",
            "sonetteanorpheus-dc282"
        ]
    },
    {
        "id": "189493",
        "time": "1771514497192",
        "appid": "29c67a55d173ee9d9ef6522dd9a05cea",
        "session": "i2IE4",
        "bereich": "reader_sonetteanorpheus",
        "item": "page44",
        "action": "enter",
        "value": "0.3814",
        "words": "47",
        "elementids": [
            "sonetteanorpheus-03ec6",
            "sonetteanorpheus-7fba1",
            "sonetteanorpheus-c5b3f"
        ]
    },
    {
        "id": "189494",
        "time": "1771514497393",
        "appid": "29c67a55d173ee9d9ef6522dd9a05cea",
        "session": "i2IE4",
        "bereich": "reader_sonetteanorpheus",
        "item": "page45",
        "action": "enter",
        "value": "0.3898",
        "words": "39",
        "elementids": [
            "sonetteanorpheus-083ec",
            "sonetteanorpheus-0a5a3",
            "sonetteanorpheus-221ff",
            "sonetteanorpheus-2ce36",
            "sonetteanorpheus-4d6f7",
            "sonetteanorpheus-55b9e",
            "sonetteanorpheus-56626",
            "sonetteanorpheus-56d34",
            "sonetteanorpheus-5ca18",
            "sonetteanorpheus-70e16",
            "sonetteanorpheus-94378",
            "sonetteanorpheus-c7f8c",
            "sonetteanorpheus-ce212",
            "sonetteanorpheus-e91ae",
            "sonetteanorpheus-ecd47"
        ]
    },
    {
        "id": "189495",
        "time": "1771514497545",
        "appid": "29c67a55d173ee9d9ef6522dd9a05cea",
        "session": "i2IE4",
        "bereich": "reader_sonetteanorpheus",
        "item": "page46",
        "action": "enter",
        "value": "0.3983",
        "words": "39",
        "elementids": [
            "sonetteanorpheus-05131",
            "sonetteanorpheus-2be7d",
            "sonetteanorpheus-304f8",
            "sonetteanorpheus-3ba63",
            "sonetteanorpheus-40232",
            "sonetteanorpheus-41413",
            "sonetteanorpheus-54cc4",
            "sonetteanorpheus-7cf73",
            "sonetteanorpheus-8494a",
            "sonetteanorpheus-895d1",
            "sonetteanorpheus-bd586",
            "sonetteanorpheus-be3b3",
            "sonetteanorpheus-c4a11",
            "sonetteanorpheus-db0b9",
            "sonetteanorpheus-e406f"
        ]
    },
    {
        "id": "189496",
        "time": "1771514500222",
        "appid": "29c67a55d173ee9d9ef6522dd9a05cea",
        "session": "i2IE4",
        "bereich": "reader_sonetteanorpheus",
        "item": "emotion",
        "action": "close",
        "value": "reject",
        "words": "0",
        "elementids": []
    },
    {
        "id": "189497",
        "time": "1771514503496",
        "appid": "29c67a55d173ee9d9ef6522dd9a05cea",
        "session": "i2IE4",
        "bereich": "reader_sonetteanorpheus",
        "item": "page47",
        "action": "enter",
        "value": "0.4068",
        "words": "8",
        "elementids": [
            "sonetteanorpheus-08e16",
            "sonetteanorpheus-82f47",
            "sonetteanorpheus-8629f"
        ]
    },
    {
        "id": "189498",
        "time": "1771514505163",
        "appid": "29c67a55d173ee9d9ef6522dd9a05cea",
        "session": "i2IE4",
        "bereich": "reader_sonetteanorpheus",
        "item": "page48",
        "action": "enter",
        "value": "0.4153",
        "words": "52",
        "elementids": [
            "sonetteanorpheus-6ffe9",
            "sonetteanorpheus-728fd",
            "sonetteanorpheus-75192",
            "sonetteanorpheus-76bfb",
            "sonetteanorpheus-796c6",
            "sonetteanorpheus-a909a",
            "sonetteanorpheus-df364",
            "sonetteanorpheus-e225f",
            "sonetteanorpheus-ec3a5"
        ]
    },
    {
        "id": "189499",
        "time": "1771514508163",
        "appid": "29c67a55d173ee9d9ef6522dd9a05cea",
        "session": "i2IE4",
        "bereich": "reader_sonetteanorpheus",
        "item": "page49",
        "action": "enter",
        "value": "0.4237",
        "words": "43",
        "elementids": [
            "sonetteanorpheus-23098",
            "sonetteanorpheus-2b749",
            "sonetteanorpheus-44003",
            "sonetteanorpheus-44b09",
            "sonetteanorpheus-63f0c",
            "sonetteanorpheus-728fd",
            "sonetteanorpheus-b2569",
            "sonetteanorpheus-b36f9",
            "sonetteanorpheus-d4159",
            "sonetteanorpheus-d41d5"
        ]
    },
    {
        "id": "189500",
        "time": "1771514508530",
        "appid": "29c67a55d173ee9d9ef6522dd9a05cea",
        "session": "i2IE4",
        "bereich": "reader_sonetteanorpheus",
        "item": "page50",
        "action": "enter",
        "value": "0.4322",
        "words": "52",
        "elementids": [
            "sonetteanorpheus-100dc",
            "sonetteanorpheus-11095",
            "sonetteanorpheus-19599",
            "sonetteanorpheus-733a3",
            "sonetteanorpheus-79aab",
            "sonetteanorpheus-83dd9",
            "sonetteanorpheus-a37ac",
            "sonetteanorpheus-aa762",
            "sonetteanorpheus-dd2ca",
            "sonetteanorpheus-df2b9",
            "sonetteanorpheus-eaabe",
            "sonetteanorpheus-f5cd0",
            "sonetteanorpheus-f66be",
            "sonetteanorpheus-f717c",
            "sonetteanorpheus-f835b"
        ]
    },
    {
        "id": "189501",
        "time": "1771514508847",
        "appid": "29c67a55d173ee9d9ef6522dd9a05cea",
        "session": "i2IE4",
        "bereich": "reader_sonetteanorpheus",
        "item": "page51",
        "action": "enter",
        "value": "0.4407",
        "words": "47",
        "elementids": [
            "sonetteanorpheus-05de8",
            "sonetteanorpheus-0d154",
            "sonetteanorpheus-2fbdf",
            "sonetteanorpheus-4b18e",
            "sonetteanorpheus-4f06c",
            "sonetteanorpheus-5b5c1",
            "sonetteanorpheus-6fe40",
            "sonetteanorpheus-768bf",
            "sonetteanorpheus-b519f"
        ]
    },
    {
        "id": "189502",
        "time": "1771514509196",
        "appid": "29c67a55d173ee9d9ef6522dd9a05cea",
        "session": "i2IE4",
        "bereich": "reader_sonetteanorpheus",
        "item": "page52",
        "action": "enter",
        "value": "0.4492",
        "words": "60",
        "elementids": [
            "sonetteanorpheus-1a781",
            "sonetteanorpheus-5f73b",
            "sonetteanorpheus-60cc3",
            "sonetteanorpheus-775d6",
            "sonetteanorpheus-78349",
            "sonetteanorpheus-8a434",
            "sonetteanorpheus-9ef5f",
            "sonetteanorpheus-a8f12",
            "sonetteanorpheus-e1a5b"
        ]
    },
    {
        "id": "189503",
        "time": "1771514509446",
        "appid": "29c67a55d173ee9d9ef6522dd9a05cea",
        "session": "i2IE4",
        "bereich": "reader_sonetteanorpheus",
        "item": "page53",
        "action": "enter",
        "value": "0.4576",
        "words": "48",
        "elementids": [
            "sonetteanorpheus-09290",
            "sonetteanorpheus-148e4",
            "sonetteanorpheus-3d4a1",
            "sonetteanorpheus-5867d",
            "sonetteanorpheus-62bc9",
            "sonetteanorpheus-7c3ba",
            "sonetteanorpheus-8a8ff",
            "sonetteanorpheus-e5b28"
        ]
    },
    {
        "id": "189504",
        "time": "1771514509679",
        "appid": "29c67a55d173ee9d9ef6522dd9a05cea",
        "session": "i2IE4",
        "bereich": "reader_sonetteanorpheus",
        "item": "page54",
        "action": "enter",
        "value": "0.4661",
        "words": "35",
        "elementids": [
            "sonetteanorpheus-00336",
            "sonetteanorpheus-6449e",
            "sonetteanorpheus-6aeae",
            "sonetteanorpheus-77741",
            "sonetteanorpheus-78cd0",
            "sonetteanorpheus-83cbd",
            "sonetteanorpheus-b62b6",
            "sonetteanorpheus-cd358",
            "sonetteanorpheus-d11a8",
            "sonetteanorpheus-da4af",
            "sonetteanorpheus-eb77b",
            "sonetteanorpheus-f367b"
        ]
    },
    {
        "id": "189505",
        "time": "1771514509863",
        "appid": "29c67a55d173ee9d9ef6522dd9a05cea",
        "session": "i2IE4",
        "bereich": "reader_sonetteanorpheus",
        "item": "page55",
        "action": "enter",
        "value": "0.4746",
        "words": "24",
        "elementids": [
            "sonetteanorpheus-014c4",
            "sonetteanorpheus-045c6",
            "sonetteanorpheus-89aab",
            "sonetteanorpheus-a9177",
            "sonetteanorpheus-b369b",
            "sonetteanorpheus-f44bc"
        ]
    },
    {
        "id": "189506",
        "time": "1771514510076",
        "appid": "29c67a55d173ee9d9ef6522dd9a05cea",
        "session": "i2IE4",
        "bereich": "reader_sonetteanorpheus",
        "item": "page56",
        "action": "enter",
        "value": "0.4831",
        "words": "43",
        "elementids": [
            "sonetteanorpheus-03267",
            "sonetteanorpheus-084dc",
            "sonetteanorpheus-11665",
            "sonetteanorpheus-1fc65",
            "sonetteanorpheus-437c9",
            "sonetteanorpheus-76d5f",
            "sonetteanorpheus-b1eeb",
            "sonetteanorpheus-c1f39",
            "sonetteanorpheus-d5aeb",
            "sonetteanorpheus-e2071",
            "sonetteanorpheus-eecb8"
        ]
    },
    {
        "id": "189507",
        "time": "1771514513412",
        "appid": "29c67a55d173ee9d9ef6522dd9a05cea",
        "session": "i2IE4",
        "bereich": "reader_sonetteanorpheus",
        "item": "page57",
        "action": "enter",
        "value": "0.4915",
        "words": "32",
        "elementids": [
            "sonetteanorpheus-0c35c",
            "sonetteanorpheus-54b9e",
            "sonetteanorpheus-65f65",
            "sonetteanorpheus-7137c",
            "sonetteanorpheus-82278",
            "sonetteanorpheus-96d40",
            "sonetteanorpheus-cbe0b"
        ]
    },
    {
        "id": "189508",
        "time": "1771514520950",
        "appid": "29c67a55d173ee9d9ef6522dd9a05cea",
        "session": "i2IE4",
        "bereich": "home",
        "item": "",
        "action": "enter",
        "value": "",
        "words": "0",
        "elementids": []
    },
    {
        "id": "189509",
        "time": "1771514528040",
        "appid": "29c67a55d173ee9d9ef6522dd9a05cea",
        "session": "i2IE4",
        "bereich": "login",
        "item": "",
        "action": "enter",
        "value": "",
        "words": "0",
        "elementids": []
    },
    {
        "id": "189510",
        "time": "1771514547553",
        "appid": "29c67a55d173ee9d9ef6522dd9a05cea",
        "session": "i2IE4",
        "bereich": "register",
        "item": "",
        "action": "enter",
        "value": "",
        "words": "0",
        "elementids": []
    },
    {
        "id": "189511",
        "time": "1771530590655",
        "appid": "29c67a55d173ee9d9ef6522dd9a05cea",
        "session": "QyxxQ",
        "bereich": "start",
        "item": "",
        "action": "enter",
        "value": "",
        "words": "0",
        "elementids": []
    },
    {
        "id": "189512",
        "time": "1771530590669",
        "appid": "29c67a55d173ee9d9ef6522dd9a05cea",
        "session": "QyxxQ",
        "bereich": "reader_sonetteanorpheus",
        "item": "",
        "action": "enter",
        "value": "sonetteanorpheus",
        "words": "0",
        "elementids": []
    },
    {
        "id": "189513",
        "time": "1771530591407",
        "appid": "29c67a55d173ee9d9ef6522dd9a05cea",
        "session": "QyxxQ",
        "bereich": "reader_sonetteanorpheus",
        "item": "page57",
        "action": "enter",
        "value": "0.4915",
        "words": "32",
        "elementids": [
            "sonetteanorpheus-0c35c",
            "sonetteanorpheus-54b9e",
            "sonetteanorpheus-65f65",
            "sonetteanorpheus-7137c",
            "sonetteanorpheus-82278",
            "sonetteanorpheus-96d40",
            "sonetteanorpheus-cbe0b"
        ]
    },
    {
        "id": "189514",
        "time": "1771530613356",
        "appid": "29c67a55d173ee9d9ef6522dd9a05cea",
        "session": "QyxxQ",
        "bereich": "reader_sonetteanorpheus",
        "item": "page58",
        "action": "leave",
        "value": "0.4831",
        "words": "32",
        "elementids": [
            "sonetteanorpheus-0c35c",
            "sonetteanorpheus-54b9e",
            "sonetteanorpheus-65f65",
            "sonetteanorpheus-7137c",
            "sonetteanorpheus-82278",
            "sonetteanorpheus-96d40",
            "sonetteanorpheus-cbe0b"
        ]
    },
    {
        "id": "189515",
        "time": "1771530717718",
        "appid": "29c67a55d173ee9d9ef6522dd9a05cea",
        "session": "YUkkb",
        "bereich": "reader_sonetteanorpheus",
        "item": "page58",
        "action": "reenter",
        "value": "0.4831",
        "words": "32",
        "elementids": [
            "sonetteanorpheus-0c35c",
            "sonetteanorpheus-54b9e",
            "sonetteanorpheus-65f65",
            "sonetteanorpheus-7137c",
            "sonetteanorpheus-82278",
            "sonetteanorpheus-96d40",
            "sonetteanorpheus-cbe0b"
        ]
    },
    {
        "id": "189516",
        "time": "1771530720417",
        "appid": "29c67a55d173ee9d9ef6522dd9a05cea",
        "session": "YUkkb",
        "bereich": "reader_sonetteanorpheus",
        "item": "page58",
        "action": "leave",
        "value": "0.4831",
        "words": "32",
        "elementids": [
            "sonetteanorpheus-0c35c",
            "sonetteanorpheus-54b9e",
            "sonetteanorpheus-65f65",
            "sonetteanorpheus-7137c",
            "sonetteanorpheus-82278",
            "sonetteanorpheus-96d40",
            "sonetteanorpheus-cbe0b"
        ]
    },
    {
        "id": "189517",
        "time": "1771531104139",
        "appid": "1c21b86bfa6e2c0ef0226b1a0b96ca7c",
        "session": "wHPEg",
        "bereich": "start",
        "item": "",
        "action": "enter",
        "value": "",
        "words": "0",
        "elementids": []
    },
    {
        "id": "189518",
        "time": "1771531105187",
        "appid": "1c21b86bfa6e2c0ef0226b1a0b96ca7c",
        "session": "wHPEg",
        "bereich": "home",
        "item": "",
        "action": "enter",
        "value": "",
        "words": "0",
        "elementids": []
    },
    {
        "id": "189519",
        "time": "1771531106202",
        "appid": "1c21b86bfa6e2c0ef0226b1a0b96ca7c",
        "session": "wHPEg",
        "bereich": "fifty-saetze",
        "item": "",
        "action": "enter",
        "value": "",
        "words": "0",
        "elementids": []
    },
    {
        "id": "189520",
        "time": "1771531107073",
        "appid": "1c21b86bfa6e2c0ef0226b1a0b96ca7c",
        "session": "wHPEg",
        "bereich": "reader_antonreiser",
        "item": "",
        "action": "enter",
        "value": "antonreiser",
        "words": "0",
        "elementids": []
    },
    {
        "id": "189521",
        "time": "1771531108124",
        "appid": "1c21b86bfa6e2c0ef0226b1a0b96ca7c",
        "session": "wHPEg",
        "bereich": "reader_antonreiser",
        "item": "page68",
        "action": "enter",
        "value": "0.0548",
        "words": "105",
        "elementids": [
            "antonreiser-153dd",
            "antonreiser-1feef",
            "antonreiser-a9a44"
        ]
    },
    {
        "id": "189522",
        "time": "1771531108405",
        "appid": "1c21b86bfa6e2c0ef0226b1a0b96ca7c",
        "session": "wHPEg",
        "bereich": "reader_antonreiser",
        "item": "page69",
        "action": "enter",
        "value": "0.0556",
        "words": "94",
        "elementids": [
            "antonreiser-045ef",
            "antonreiser-0cf71",
            "antonreiser-1f3b4",
            "antonreiser-2b1e2",
            "antonreiser-c1b5f"
        ]
    },
    {
        "id": "189523",
        "time": "1771531111315",
        "appid": "1c21b86bfa6e2c0ef0226b1a0b96ca7c",
        "session": "wHPEg",
        "bereich": "reader_antonreiser",
        "item": "location",
        "action": "set",
        "value": "ort-3",
        "words": "0",
        "elementids": []
    },
    {
        "id": "189524",
        "time": "1771540347712",
        "appid": "7b8d43e31532f543851521d98711d418",
        "session": "Gaz8C",
        "bereich": "start",
        "item": "",
        "action": "enter",
        "value": "",
        "words": "0",
        "elementids": []
    },
    {
        "id": "189525",
        "time": "1771540347727",
        "appid": "7b8d43e31532f543851521d98711d418",
        "session": "Gaz8C",
        "bereich": "reader_lenz",
        "item": "",
        "action": "enter",
        "value": "lenz",
        "words": "0",
        "elementids": []
    },
    {
        "id": "189526",
        "time": "1771540348428",
        "appid": "7b8d43e31532f543851521d98711d418",
        "session": "Gaz8C",
        "bereich": "reader_lenz",
        "item": "page12",
        "action": "enter",
        "value": "0.619",
        "words": "424",
        "elementids": [
            "lenz-00899",
            "lenz-1e60e",
            "lenz-4d386",
            "lenz-52bf3",
            "lenz-7e396",
            "lenz-7f4f8",
            "lenz-7fc4a",
            "lenz-8a8e2",
            "lenz-8da39",
            "lenz-90f93",
            "lenz-9c15f",
            "lenz-9d58d",
            "lenz-a0efc",
            "lenz-a3bf7",
            "lenz-b75de",
            "lenz-beea5",
            "lenz-c2721",
            "lenz-c3edc",
            "lenz-cdfb3",
            "lenz-d094d",
            "lenz-d7c12",
            "lenz-e1ca9",
            "lenz-e803e",
            "lenz-ee83a",
            "lenz-f041c",
            "lenz-f2b5b"
        ]
    },
    {
        "id": "189527",
        "time": "1771540357599",
        "appid": "7b8d43e31532f543851521d98711d418",
        "session": "Gaz8C",
        "bereich": "reader_lenz",
        "item": "page13",
        "action": "enter",
        "value": "0.6667",
        "words": "453",
        "elementids": [
            "lenz-0b4ba",
            "lenz-13285",
            "lenz-190c8",
            "lenz-1e0ba",
            "lenz-22d6f",
            "lenz-28e21",
            "lenz-2aaef",
            "lenz-2c5aa",
            "lenz-337ed",
            "lenz-3e773",
            "lenz-3f5e4",
            "lenz-3f683",
            "lenz-6a7e9",
            "lenz-6c417",
            "lenz-9e545",
            "lenz-a8b48",
            "lenz-ac9dd",
            "lenz-ba6dc",
            "lenz-bd302",
            "lenz-c5dcc",
            "lenz-c9bb2",
            "lenz-cbb09",
            "lenz-cfb63",
            "lenz-d493f",
            "lenz-e39d6",
            "lenz-f2ab5"
        ]
    },
    {
        "id": "189528",
        "time": "1771540380276",
        "appid": "7b8d43e31532f543851521d98711d418",
        "session": "Gaz8C",
        "bereich": "reader_lenz",
        "item": "location",
        "action": "set",
        "value": "ort-3",
        "words": "0",
        "elementids": []
    },
    {
        "id": "189529",
        "time": "1771540389246",
        "appid": "7b8d43e31532f543851521d98711d418",
        "session": "Gaz8C",
        "bereich": "reader_lenz",
        "item": "page12",
        "action": "enter",
        "value": "0.619",
        "words": "424",
        "elementids": [
            "lenz-00899",
            "lenz-1e60e",
            "lenz-4d386",
            "lenz-52bf3",
            "lenz-7e396",
            "lenz-7f4f8",
            "lenz-7fc4a",
            "lenz-8a8e2",
            "lenz-8da39",
            "lenz-90f93",
            "lenz-9c15f",
            "lenz-9d58d",
            "lenz-a0efc",
            "lenz-a3bf7",
            "lenz-b75de",
            "lenz-beea5",
            "lenz-c2721",
            "lenz-c3edc",
            "lenz-cdfb3",
            "lenz-d094d",
            "lenz-d7c12",
            "lenz-e1ca9",
            "lenz-e803e",
            "lenz-ee83a",
            "lenz-f041c",
            "lenz-f2b5b"
        ]
    },
    {
        "id": "189530",
        "time": "1771540390227",
        "appid": "7b8d43e31532f543851521d98711d418",
        "session": "Gaz8C",
        "bereich": "reader_lenz",
        "item": "page11",
        "action": "enter",
        "value": "0.5714",
        "words": "435",
        "elementids": [
            "lenz-08c01",
            "lenz-19baa",
            "lenz-2458b",
            "lenz-29326",
            "lenz-2f541",
            "lenz-35385",
            "lenz-37af1",
            "lenz-47bfb",
            "lenz-4a199",
            "lenz-5ae19",
            "lenz-73062",
            "lenz-806c6",
            "lenz-841e5",
            "lenz-96467",
            "lenz-9c038",
            "lenz-9d58d",
            "lenz-a9183",
            "lenz-ac2ec",
            "lenz-aec63",
            "lenz-af5e3",
            "lenz-b74b3",
            "lenz-bfbdc",
            "lenz-cc896",
            "lenz-f0166",
            "lenz-f79d1",
            "lenz-fdd72"
        ]
    },
    {
        "id": "189531",
        "time": "1771540390878",
        "appid": "7b8d43e31532f543851521d98711d418",
        "session": "Gaz8C",
        "bereich": "reader_lenz",
        "item": "page10",
        "action": "enter",
        "value": "0.5238",
        "words": "472",
        "elementids": [
            "lenz-0867a",
            "lenz-123cd",
            "lenz-1249c",
            "lenz-15bf4",
            "lenz-1a8d4",
            "lenz-1d4fb",
            "lenz-21973",
            "lenz-225f4",
            "lenz-22a2c",
            "lenz-2d570",
            "lenz-30ddb",
            "lenz-33ffd",
            "lenz-40f1e",
            "lenz-53ad7",
            "lenz-62cbc",
            "lenz-64923",
            "lenz-66097",
            "lenz-6bb56",
            "lenz-6e23a",
            "lenz-72aea",
            "lenz-76fea",
            "lenz-7f8c2",
            "lenz-810c7",
            "lenz-89c59",
            "lenz-8cd56",
            "lenz-8fb90",
            "lenz-8fe92",
            "lenz-92f5a",
            "lenz-94b92",
            "lenz-9919e",
            "lenz-9c190",
            "lenz-a28fb",
            "lenz-b24ce",
            "lenz-b2591",
            "lenz-b3de3",
            "lenz-c86e2",
            "lenz-cc896",
            "lenz-cccca",
            "lenz-ecdc7",
            "lenz-ef5c2",
            "lenz-fe65c"
        ]
    },
    {
        "id": "189532",
        "time": "1771540391396",
        "appid": "7b8d43e31532f543851521d98711d418",
        "session": "Gaz8C",
        "bereich": "reader_lenz",
        "item": "page9",
        "action": "enter",
        "value": "0.4762",
        "words": "446",
        "elementids": [
            "lenz-0d956",
            "lenz-16914",
            "lenz-1c4cb",
            "lenz-1d947",
            "lenz-2908a",
            "lenz-2a372",
            "lenz-3aaad",
            "lenz-43503",
            "lenz-4a616",
            "lenz-8ae2b",
            "lenz-964f4",
            "lenz-994ff",
            "lenz-9c751",
            "lenz-a7579",
            "lenz-b87dd",
            "lenz-be5d6",
            "lenz-c908f",
            "lenz-e386b",
            "lenz-e4491",
            "lenz-ea3f4",
            "lenz-ef5c2",
            "lenz-f268c"
        ]
    },
    {
        "id": "189533",
        "time": "1771540391844",
        "appid": "7b8d43e31532f543851521d98711d418",
        "session": "Gaz8C",
        "bereich": "reader_lenz",
        "item": "page8",
        "action": "enter",
        "value": "0.4286",
        "words": "460",
        "elementids": [
            "lenz-072c9",
            "lenz-0a5c7",
            "lenz-1076b",
            "lenz-12f7e",
            "lenz-204b9",
            "lenz-22b9c",
            "lenz-2958f",
            "lenz-4a616",
            "lenz-50a9e",
            "lenz-5a67f",
            "lenz-99901",
            "lenz-a35ed",
            "lenz-ae16c",
            "lenz-b93e6",
            "lenz-bbf3f",
            "lenz-c382a",
            "lenz-c8dde",
            "lenz-cbafe",
            "lenz-cdf32",
            "lenz-e78a8",
            "lenz-f47a3",
            "lenz-f5d6f"
        ]
    },
    {
        "id": "189534",
        "time": "1771540392328",
        "appid": "7b8d43e31532f543851521d98711d418",
        "session": "Gaz8C",
        "bereich": "reader_lenz",
        "item": "page7",
        "action": "enter",
        "value": "0.381",
        "words": "470",
        "elementids": [
            "lenz-04e12",
            "lenz-132a0",
            "lenz-15236",
            "lenz-28e40",
            "lenz-5031e",
            "lenz-529e4",
            "lenz-738a5",
            "lenz-82abd",
            "lenz-92efe",
            "lenz-a4cd7",
            "lenz-c1f38",
            "lenz-de016",
            "lenz-e1d4b",
            "lenz-e4790",
            "lenz-f3681",
            "lenz-f47a3"
        ]
    },
    {
        "id": "189535",
        "time": "1771540392811",
        "appid": "7b8d43e31532f543851521d98711d418",
        "session": "Gaz8C",
        "bereich": "reader_lenz",
        "item": "page6",
        "action": "enter",
        "value": "0.3333",
        "words": "402",
        "elementids": [
            "lenz-04e12",
            "lenz-05b2e",
            "lenz-20eda",
            "lenz-24850",
            "lenz-30c4d",
            "lenz-67d92",
            "lenz-68905",
            "lenz-696c2",
            "lenz-6e727",
            "lenz-7f8a7",
            "lenz-82050",
            "lenz-83058",
            "lenz-89114",
            "lenz-8c436",
            "lenz-91d46",
            "lenz-a26c6",
            "lenz-aa2a6",
            "lenz-ae8d5",
            "lenz-b4458",
            "lenz-b8e7e",
            "lenz-ca117",
            "lenz-e09eb"
        ]
    },
    {
        "id": "189536",
        "time": "1771540393262",
        "appid": "7b8d43e31532f543851521d98711d418",
        "session": "Gaz8C",
        "bereich": "reader_lenz",
        "item": "page5",
        "action": "enter",
        "value": "0.2857",
        "words": "440",
        "elementids": [
            "lenz-09b86",
            "lenz-14192",
            "lenz-1b401",
            "lenz-1df71",
            "lenz-280b3",
            "lenz-2b79d",
            "lenz-331d2",
            "lenz-3b041",
            "lenz-53d5e",
            "lenz-55dd1",
            "lenz-58dcd",
            "lenz-59188",
            "lenz-5e843",
            "lenz-62f72",
            "lenz-683ff",
            "lenz-6d492",
            "lenz-7188e",
            "lenz-7f8a7",
            "lenz-917a1",
            "lenz-a2680",
            "lenz-ada9f",
            "lenz-b7d71",
            "lenz-c24ff"
        ]
    },
    {
        "id": "189537",
        "time": "1771540394595",
        "appid": "7b8d43e31532f543851521d98711d418",
        "session": "Gaz8C",
        "bereich": "reader_lenz",
        "item": "page4",
        "action": "enter",
        "value": "0.2381",
        "words": "439",
        "elementids": [
            "lenz-0167f",
            "lenz-01ee9",
            "lenz-05018",
            "lenz-086e4",
            "lenz-0c6ac",
            "lenz-0f0e6",
            "lenz-0f2a0",
            "lenz-26d61",
            "lenz-28a24",
            "lenz-41e4f",
            "lenz-54b45",
            "lenz-6d74f",
            "lenz-7c6c5",
            "lenz-7f202",
            "lenz-874c0",
            "lenz-91e34",
            "lenz-a0579",
            "lenz-ca3bf",
            "lenz-cbbec",
            "lenz-ebc41",
            "lenz-f11b1"
        ]
    },
    {
        "id": "189538",
        "time": "1771540395062",
        "appid": "7b8d43e31532f543851521d98711d418",
        "session": "Gaz8C",
        "bereich": "reader_lenz",
        "item": "page3",
        "action": "enter",
        "value": "0.1905",
        "words": "456",
        "elementids": [
            "lenz-0d54f",
            "lenz-26d84",
            "lenz-28a24",
            "lenz-2ea64",
            "lenz-3f771",
            "lenz-40402",
            "lenz-4e0be",
            "lenz-55890",
            "lenz-57150",
            "lenz-5737e",
            "lenz-662a6",
            "lenz-66681",
            "lenz-688ca",
            "lenz-81058",
            "lenz-9e19e",
            "lenz-b5ab9",
            "lenz-bb6f7",
            "lenz-c5e82",
            "lenz-c629d",
            "lenz-ceabc",
            "lenz-d9bb1",
            "lenz-e8c86",
            "lenz-f7848"
        ]
    },
    {
        "id": "189539",
        "time": "1771540395796",
        "appid": "7b8d43e31532f543851521d98711d418",
        "session": "Gaz8C",
        "bereich": "reader_lenz",
        "item": "page2",
        "action": "enter",
        "value": "0.1429",
        "words": "396",
        "elementids": [
            "lenz-11f9b",
            "lenz-14000",
            "lenz-174af",
            "lenz-1ad51",
            "lenz-238cf",
            "lenz-428c6",
            "lenz-587f0",
            "lenz-5af55",
            "lenz-5fde6",
            "lenz-648d0",
            "lenz-73699",
            "lenz-82535",
            "lenz-924df",
            "lenz-a10b1",
            "lenz-a7e66",
            "lenz-add51",
            "lenz-bb2e3",
            "lenz-c5b9f",
            "lenz-c7944",
            "lenz-c7d0e",
            "lenz-d83fb",
            "lenz-d891e",
            "lenz-e1b01",
            "lenz-fac9b"
        ]
    },
    {
        "id": "189540",
        "time": "1771540396214",
        "appid": "7b8d43e31532f543851521d98711d418",
        "session": "Gaz8C",
        "bereich": "reader_lenz",
        "item": "page1",
        "action": "enter",
        "value": "0.0952",
        "words": "411",
        "elementids": [
            "lenz-049a7",
            "lenz-06304",
            "lenz-14000",
            "lenz-21302",
            "lenz-24794",
            "lenz-45c2a",
            "lenz-533b1",
            "lenz-5ab3a",
            "lenz-6bcb1",
            "lenz-70f52",
            "lenz-79ed2",
            "lenz-b7b14",
            "lenz-c9b9d",
            "lenz-cc49f",
            "lenz-f5d9b"
        ]
    },
    {
        "id": "189541",
        "time": "1771540411447",
        "appid": "7b8d43e31532f543851521d98711d418",
        "session": "Gaz8C",
        "bereich": "login",
        "item": "",
        "action": "enter",
        "value": "",
        "words": "0",
        "elementids": []
    },
    {
        "id": "189542",
        "time": "1771540546773",
        "appid": "7b8d43e31532f543851521d98711d418",
        "session": "Gaz8C",
        "bereich": "reader_lenz",
        "item": "",
        "action": "enter",
        "value": "lenz",
        "words": "0",
        "elementids": []
    },
    {
        "id": "189543",
        "time": "1771540546797",
        "appid": "7b8d43e31532f543851521d98711d418",
        "session": "Gaz8C",
        "bereich": "reader_lenz",
        "item": "page1",
        "action": "enter",
        "value": "0.0952",
        "words": "411",
        "elementids": [
            "lenz-049a7",
            "lenz-06304",
            "lenz-14000",
            "lenz-21302",
            "lenz-24794",
            "lenz-45c2a",
            "lenz-533b1",
            "lenz-5ab3a",
            "lenz-6bcb1",
            "lenz-70f52",
            "lenz-79ed2",
            "lenz-b7b14",
            "lenz-c9b9d",
            "lenz-cc49f",
            "lenz-f5d9b"
        ]
    },
    {
        "id": "189544",
        "time": "1771540552323",
        "appid": "7b8d43e31532f543851521d98711d418",
        "session": "Gaz8C",
        "bereich": "home",
        "item": "",
        "action": "enter",
        "value": "",
        "words": "0",
        "elementids": []
    },
    {
        "id": "189545",
        "time": "1771540554400",
        "appid": "7b8d43e31532f543851521d98711d418",
        "session": "Gaz8C",
        "bereich": "zu-den-texten",
        "item": "",
        "action": "enter",
        "value": "",
        "words": "0",
        "elementids": []
    },
    {
        "id": "189546",
        "time": "1771540567322",
        "appid": "7b8d43e31532f543851521d98711d418",
        "session": "Gaz8C",
        "bereich": "titelblatt_sonetteanorpheus",
        "item": "",
        "action": "enter",
        "value": "sonetteanorpheus",
        "words": "0",
        "elementids": []
    },
    {
        "id": "189547",
        "time": "1771540571139",
        "appid": "7b8d43e31532f543851521d98711d418",
        "session": "Gaz8C",
        "bereich": "reader_sonetteanorpheus",
        "item": "",
        "action": "enter",
        "value": "sonetteanorpheus",
        "words": "0",
        "elementids": []
    },
    {
        "id": "189548",
        "time": "1771540664478",
        "appid": "7b8d43e31532f543851521d98711d418",
        "session": "Gaz8C",
        "bereich": "reader_sonetteanorpheus",
        "item": "mindwandering",
        "action": "notdepends",
        "value": "0",
        "words": "0",
        "elementids": []
    },
    {
        "id": "189549",
        "time": "1771540735462",
        "appid": "7b8d43e31532f543851521d98711d418",
        "session": "Gaz8C",
        "bereich": "reader_sonetteanorpheus",
        "item": "page2",
        "action": "enter",
        "value": "0.0484",
        "words": "97",
        "elementids": [
            "sonetteanorpheus-09410",
            "sonetteanorpheus-0b41a",
            "sonetteanorpheus-0c5a4",
            "sonetteanorpheus-11d21",
            "sonetteanorpheus-16400",
            "sonetteanorpheus-1daab",
            "sonetteanorpheus-224de",
            "sonetteanorpheus-27a6f",
            "sonetteanorpheus-2a091",
            "sonetteanorpheus-2aa2d",
            "sonetteanorpheus-2f5a3",
            "sonetteanorpheus-446b7",
            "sonetteanorpheus-6bdee",
            "sonetteanorpheus-a36f0",
            "sonetteanorpheus-a654b",
            "sonetteanorpheus-abce9",
            "sonetteanorpheus-bcf98",
            "sonetteanorpheus-ca33d",
            "sonetteanorpheus-d5483",
            "sonetteanorpheus-db36c",
            "sonetteanorpheus-ee349",
            "sonetteanorpheus-efad6"
        ]
    },
    {
        "id": "189550",
        "time": "1771540747733",
        "appid": "7b8d43e31532f543851521d98711d418",
        "session": "Gaz8C",
        "bereich": "reader_sonetteanorpheus",
        "item": "location",
        "action": "set",
        "value": "ort-3",
        "words": "0",
        "elementids": []
    },
    {
        "id": "189551",
        "time": "1771540809588",
        "appid": "7b8d43e31532f543851521d98711d418",
        "session": "Gaz8C",
        "bereich": "reader_sonetteanorpheus",
        "item": "mindwandering",
        "action": "notdepends",
        "value": "1",
        "words": "0",
        "elementids": []
    },
    {
        "id": "189552",
        "time": "1771540817540",
        "appid": "7b8d43e31532f543851521d98711d418",
        "session": "Gaz8C",
        "bereich": "reader_sonetteanorpheus",
        "item": "page3",
        "action": "enter",
        "value": "0.0645",
        "words": "97",
        "elementids": [
            "sonetteanorpheus-01d28",
            "sonetteanorpheus-05f20",
            "sonetteanorpheus-0d2d0",
            "sonetteanorpheus-14d3f",
            "sonetteanorpheus-23a00",
            "sonetteanorpheus-45eaa",
            "sonetteanorpheus-49af1",
            "sonetteanorpheus-4d091",
            "sonetteanorpheus-53797",
            "sonetteanorpheus-55cc3",
            "sonetteanorpheus-55e62",
            "sonetteanorpheus-5f221",
            "sonetteanorpheus-601bc",
            "sonetteanorpheus-64fe7",
            "sonetteanorpheus-6dd2c",
            "sonetteanorpheus-6e2a6",
            "sonetteanorpheus-8c237",
            "sonetteanorpheus-9680f",
            "sonetteanorpheus-968fa",
            "sonetteanorpheus-99ad2",
            "sonetteanorpheus-a45b7",
            "sonetteanorpheus-afb13",
            "sonetteanorpheus-b9c8b",
            "sonetteanorpheus-d1b13",
            "sonetteanorpheus-d5f12",
            "sonetteanorpheus-df236",
            "sonetteanorpheus-eb4f7"
        ]
    },
    {
        "id": "189553",
        "time": "1771540874512",
        "appid": "7b8d43e31532f543851521d98711d418",
        "session": "Gaz8C",
        "bereich": "reader_sonetteanorpheus",
        "item": "page4",
        "action": "enter",
        "value": "0.0806",
        "words": "81",
        "elementids": [
            "sonetteanorpheus-025e8",
            "sonetteanorpheus-234a8",
            "sonetteanorpheus-3a6e8",
            "sonetteanorpheus-57cd8",
            "sonetteanorpheus-63bc6",
            "sonetteanorpheus-79d88",
            "sonetteanorpheus-87acb",
            "sonetteanorpheus-9b137",
            "sonetteanorpheus-a0604",
            "sonetteanorpheus-a38e6",
            "sonetteanorpheus-c1d57",
            "sonetteanorpheus-c2dd3",
            "sonetteanorpheus-c90e6",
            "sonetteanorpheus-da34c",
            "sonetteanorpheus-e7204",
            "sonetteanorpheus-f8c30"
        ]
    },
    {
        "id": "189554",
        "time": "1771540888550",
        "appid": "7b8d43e31532f543851521d98711d418",
        "session": "Gaz8C",
        "bereich": "reader_sonetteanorpheus",
        "item": "page5",
        "action": "enter",
        "value": "0.0968",
        "words": "89",
        "elementids": [
            "sonetteanorpheus-04014",
            "sonetteanorpheus-09a26",
            "sonetteanorpheus-0b834",
            "sonetteanorpheus-1a032",
            "sonetteanorpheus-21081",
            "sonetteanorpheus-23ca4",
            "sonetteanorpheus-259f9",
            "sonetteanorpheus-3edb5",
            "sonetteanorpheus-4e8f4",
            "sonetteanorpheus-572eb",
            "sonetteanorpheus-5d55c",
            "sonetteanorpheus-6faa6",
            "sonetteanorpheus-8175d",
            "sonetteanorpheus-91173",
            "sonetteanorpheus-a382a",
            "sonetteanorpheus-a4e9f",
            "sonetteanorpheus-b17ed",
            "sonetteanorpheus-c4da2",
            "sonetteanorpheus-cd2df",
            "sonetteanorpheus-f69b4"
        ]
    },
    {
        "id": "189555",
        "time": "1771540889553",
        "appid": "7b8d43e31532f543851521d98711d418",
        "session": "Gaz8C",
        "bereich": "reader_sonetteanorpheus",
        "item": "page4",
        "action": "enter",
        "value": "0.0806",
        "words": "81",
        "elementids": [
            "sonetteanorpheus-025e8",
            "sonetteanorpheus-234a8",
            "sonetteanorpheus-3a6e8",
            "sonetteanorpheus-57cd8",
            "sonetteanorpheus-63bc6",
            "sonetteanorpheus-79d88",
            "sonetteanorpheus-87acb",
            "sonetteanorpheus-9b137",
            "sonetteanorpheus-a0604",
            "sonetteanorpheus-a38e6",
            "sonetteanorpheus-c1d57",
            "sonetteanorpheus-c2dd3",
            "sonetteanorpheus-c90e6",
            "sonetteanorpheus-da34c",
            "sonetteanorpheus-e7204",
            "sonetteanorpheus-f8c30"
        ]
    },
    {
        "id": "189556",
        "time": "1771540893186",
        "appid": "7b8d43e31532f543851521d98711d418",
        "session": "Gaz8C",
        "bereich": "reader_sonetteanorpheus",
        "item": "page5",
        "action": "leave",
        "value": "0.0645",
        "words": "81",
        "elementids": [
            "sonetteanorpheus-025e8",
            "sonetteanorpheus-234a8",
            "sonetteanorpheus-3a6e8",
            "sonetteanorpheus-57cd8",
            "sonetteanorpheus-63bc6",
            "sonetteanorpheus-79d88",
            "sonetteanorpheus-87acb",
            "sonetteanorpheus-9b137",
            "sonetteanorpheus-a0604",
            "sonetteanorpheus-a38e6",
            "sonetteanorpheus-c1d57",
            "sonetteanorpheus-c2dd3",
            "sonetteanorpheus-c90e6",
            "sonetteanorpheus-da34c",
            "sonetteanorpheus-e7204",
            "sonetteanorpheus-f8c30"
        ]
    }
]